Workbook

Sheet Lisez-moi
A1: Plan de scaling — rachat de comptes mois après mois
A3: Pour Google Sheets : Fichier > Importer > Importer les données (remplacer la feuille). Les cellules bleues (onglet Paramètres) sont modifiables ; la Simulation et les Graphiques se recalculent.
A5: LE PRINCIPE (votre méthode)
A6: Vous partez d'un compte direct FundedNext de 10 000 $. Chaque mois vous prenez un payout de 10 % du capital, la firme garde 30 %, vous gardez donc 70 %.
A7: Vous accumulez cet argent, et dès que vous le pouvez, vous rachetez le plus GROS compte que votre trésorerie permet (catalogue des comptes, prix le moins cher par taille). Puis vous recommencez chaque mois : payout, on accumule, on rachète le plus gros possible.
A8: Plus vous avez de comptes, plus le payout mensuel est gros, donc plus vous rachetez vite : c'est l'effet boule de neige.
A10: LES ONGLETS
A11: Paramètres : payout mensuel %, part de la firme %, capital de départ.
A12: Catalogue : les tailles de compte achetables et leur prix le moins cher (une firme par taille). C'est là qu'on pioche le plus gros compte abordable.
A13: Simulation : un mois par ligne. Capital au début, payout net encaissé, trésorerie, le compte acheté ce mois (taille + firme + prix), trésorerie restante, capital total, et le revenu mensuel que vous pourriez retirer à ce stade.
A14: Graphiques : capital total, revenu mensuel potentiel, payout cumulé.
A16: LIMITES
A17: Un seul rachat par mois par défaut (le temps de passer l'évaluation). Prix hors codes promo, catalogue filtré aux offres réalistes. Borne théorique sous rendement constant, sans échec d'évaluation ni plafond de retrait.

Sheet Paramètres
A1: Paramètres
A3: Payout mensuel (% du capital) | B3: 0.1
A4: Part de la firme (elle garde) | B4: 0.3
A5: Capital de départ (FundedNext) | B5: 10000
A7: Vous gardez 1 − part firme. Modifiez ces cellules : tout se recalcule.

Sheet Catalogue
A1: Taille ($) | B1: Prix le moins cher ($) | C1: Firme | D1: Plan | E1: Marché | F1: $ / 1000$
A2: 6000 | B2: 59 | C2: Monevis | D2: Instant | E2: CFD | F2: 9.8
A3: 7000 | B3: 52 | C3: Prop Number One | D3: 2 étapes | E3: CFD | F3: 7.4
A4: 7500 | B4: 59 | C4: EverBlue Trader | D4: 2 étapes | E4: CFD | F4: 7.9
A5: 8000 | B5: 89 | C5: TradersFlow | D5: 1 étape | E5: CFD | F5: 11.1
A6: 10000 | B6: 29 | C6: PaidPex | D6: 1 étape | E6: CFD | F6: 2.9
A7: 15000 | B7: 75 | C7: NowTradeFunded | D7: 2 étapes | E7: CFD | F7: 5
A8: 17000 | B8: 161 | C8: Prop Number One | D8: 2 étapes | E8: CFD | F8: 9.5
A9: 27000 | B9: 217 | C9: Prop Number One | D9: 2 étapes | E9: CFD | F9: 8
A10: 30000 | B10: 199 | C10: SFX Funded | D10: 2 étapes | E10: CFD | F10: 6.6
A11: 35000 | B11: 189 | C11: EverBlue Trader | D11: 2 étapes | E11: CFD | F11: 5.4
A12: 40000 | B12: 399 | C12: Paid To Trade | D12: 2 étapes | E12: CFD | F12: 10
A13: 60000 | B13: 299 | C13: SFX Funded | D13: 2 étapes | E13: CFD | F13: 5
... A24: 2500000 | B24: 8500 | C24: LVL Trading | D24: 1 étape | E24: Futures | F24: 3.4

Sheet Simulation
A1: Mois | B1: Capital début ($) | C1: Payout net du mois ($) | D1: Trésorerie avant achat ($) | E1: Plus gros compte achetable ($) | F1: Firme achetée | G1: Prix payé ($) | H1: Trésorerie après ($) | I1: Capital total ($) | J1: Revenu mensuel potentiel ($) | K1: Payout net cumulé ($)
A2: 1 | B2: =Paramètres!$B$5 | C2: =B2*Paramètres!$B$3*(1-Paramètres!$B$4) | D2: =C2 | E2: =IFERROR(MAXIFS(Catalogue!$A$2:$A$24,Catalogue!$B$2:$B$24,"<="&D2),0) | F2: =IF(E2=0,"—",INDEX(Catalogue!$C$2:$C$24,MATCH(E2,Catalogue!$A$2:$A$24,0))) | G2: =IF(E2=0,0,INDEX(Catalogue!$B$2:$B$24,MATCH(E2,Catalogue!$A$2:$A$24,0))) | H2: =D2-G2 | I2: =B2+E2 | J2: =I2*Paramètres!$B$3*(1-Paramètres!$B$4) | K2: =C2
A3: 2 | B3: =I2 | C3: =B3*Paramètres!$B$3*(1-Paramètres!$B$4) | D3: =H2+C3 | E3: =IFERROR(MAXIFS(Catalogue!$A$2:$A$24,Catalogue!$B$2:$B$24,"<="&D3),0) | F3: =IF(E3=0,"—",INDEX(Catalogue!$C$2:$C$24,MATCH(E3,Catalogue!$A$2:$A$24,0))) | G3: =IF(E3=0,0,INDEX(Catalogue!$B$2:$B$24,MATCH(E3,Catalogue!$A$2:$A$24,0))) | H3: =D3-G3 | I3: =B3+E3 | J3: =I3*Paramètres!$B$3*(1-Paramètres!$B$4) | K3: =K2+C3
A4: 3 | B4: =I3 | C4: =B4*Paramètres!$B$3*(1-Paramètres!$B$4) | D4: =H3+C4 | E4: =IFERROR(MAXIFS(Catalogue!$A$2:$A$24,Catalogue!$B$2:$B$24,"<="&D4),0) | F4: =IF(E4=0,"—",INDEX(Catalogue!$C$2:$C$24,MATCH(E4,Catalogue!$A$2:$A$24,0))) | G4: =IF(E4=0,0,INDEX(Catalogue!$B$2:$B$24,MATCH(E4,Catalogue!$A$2:$A$24,0))) | H4: =D4-G4 | I4: =B4+E4 | J4: =I4*Paramètres!$B$3*(1-Paramètres!$B$4) | K4: =K3+C4
A5: 4 | B5: =I4 | C5: =B5*Paramètres!$B$3*(1-Paramètres!$B$4) | D5: =H4+C5 | E5: =IFERROR(MAXIFS(Catalogue!$A$2:$A$24,Catalogue!$B$2:$B$24,"<="&D5),0) | F5: =IF(E5=0,"—",INDEX(Catalogue!$C$2:$C$24,MATCH(E5,Catalogue!$A$2:$A$24,0))) | G5: =IF(E5=0,0,INDEX(Catalogue!$B$2:$B$24,MATCH(E5,Catalogue!$A$2:$A$24,0))) | H5: =D5-G5 | I5: =B5+E5 | J5: =I5*Paramètres!$B$3*(1-Paramètres!$B$4) | K5: =K4+C5
A6: 5 | B6: =I5 | C6: =B6*Paramètres!$B$3*(1-Paramètres!$B$4) | D6: =H5+C6 | E6: =IFERROR(MAXIFS(Catalogue!$A$2:$A$24,Catalogue!$B$2:$B$24,"<="&D6),0) | F6: =IF(E6=0,"—",INDEX(Catalogue!$C$2:$C$24,MATCH(E6,Catalogue!$A$2:$A$24,0))) | G6: =IF(E6=0,0,INDEX(Catalogue!$B$2:$B$24,MATCH(E6,Catalogue!$A$2:$A$24,0))) | H6: =D6-G6 | I6: =B6+E6 | J6: =I6*Paramètres!$B$3*(1-Paramètres!$B$4) | K6: =K5+C6
A7: 6 | B7: =I6 | C7: =B7*Paramètres!$B$3*(1-Paramètres!$B$4) | D7: =H6+C7 | E7: =IFERROR(MAXIFS(Catalogue!$A$2:$A$24,Catalogue!$B$2:$B$24,"<="&D7),0) | F7: =IF(E7=0,"—",INDEX(Catalogue!$C$2:$C$24,MATCH(E7,Catalogue!$A$2:$A$24,0))) | G7: =IF(E7=0,0,INDEX(Catalogue!$B$2:$B$24,MATCH(E7,Catalogue!$A$2:$A$24,0))) | H7: =D7-G7 | I7: =B7+E7 | J7: =I7*Paramètres!$B$3*(1-Paramètres!$B$4) | K7: =K6+C7
A8: 7 | B8: =I7 | C8: =B8*Paramètres!$B$3*(1-Paramètres!$B$4) | D8: =H7+C8 | E8: =IFERROR(MAXIFS(Catalogue!$A$2:$A$24,Catalogue!$B$2:$B$24,"<="&D8),0) | F8: =IF(E8=0,"—",INDEX(Catalogue!$C$2:$C$24,MATCH(E8,Catalogue!$A$2:$A$24,0))) | G8: =IF(E8=0,0,INDEX(Catalogue!$B$2:$B$24,MATCH(E8,Catalogue!$A$2:$A$24,0))) | H8: =D8-G8 | I8: =B8+E8 | J8: =I8*Paramètres!$B$3*(1-Paramètres!$B$4) | K8: =K7+C8
A9: 8 | B9: =I8 | C9: =B9*Paramètres!$B$3*(1-Paramètres!$B$4) | D9: =H8+C9 | E9: =IFERROR(MAXIFS(Catalogue!$A$2:$A$24,Catalogue!$B$2:$B$24,"<="&D9),0) | F9: =IF(E9=0,"—",INDEX(Catalogue!$C$2:$C$24,MATCH(E9,Catalogue!$A$2:$A$24,0))) | G9: =IF(E9=0,0,INDEX(Catalogue!$B$2:$B$24,MATCH(E9,Catalogue!$A$2:$A$24,0))) | H9: =D9-G9 | I9: =B9+E9 | J9: =I9*Paramètres!$B$3*(1-Paramètres!$B$4) | K9: =K8+C9
A10: 9 | B10: =I9 | C10: =B10*Paramètres!$B$3*(1-Paramètres!$B$4) | D10: =H9+C10 | E10: =IFERROR(MAXIFS(Catalogue!$A$2:$A$24,Catalogue!$B$2:$B$24,"<="&D10),0) | F10: =IF(E10=0,"—",INDEX(Catalogue!$C$2:$C$24,MATCH(E10,Catalogue!$A$2:$A$24,0))) | G10: =IF(E10=0,0,INDEX(Catalogue!$B$2:$B$24,MATCH(E10,Catalogue!$A$2:$A$24,0))) | H10: =D10-G10 | I10: =B10+E10 | J10: =I10*Paramètres!$B$3*(1-Paramètres!$B$4) | K10: =K9+C10
A11: 10 | B11: =I10 | C11: =B11*Paramètres!$B$3*(1-Paramètres!$B$4) | D11: =H10+C11 | E11: =IFERROR(MAXIFS(Catalogue!$A$2:$A$24,Catalogue!$B$2:$B$24,"<="&D11),0) | F11: =IF(E11=0,"—",INDEX(Catalogue!$C$2:$C$24,MATCH(E11,Catalogue!$A$2:$A$24,0))) | G11: =IF(E11=0,0,INDEX(Catalogue!$B$2:$B$24,MATCH(E11,Catalogue!$A$2:$A$24,0))) | H11: =D11-G11 | I11: =B11+E11 | J11: =I11*Paramètres!$B$3*(1-Paramètres!$B$4) | K11: =K10+C11
A12: 11 | B12: =I11 | C12: =B12*Paramètres!$B$3*(1-Paramètres!$B$4) | D12: =H11+C12 | E12: =IFERROR(MAXIFS(Catalogue!$A$2:$A$24,Catalogue!$B$2:$B$24,"<="&D12),0) | F12: =IF(E12=0,"—",INDEX(Catalogue!$C$2:$C$24,MATCH(E12,Catalogue!$A$2:$A$24,0))) | G12: =IF(E12=0,0,INDEX(Catalogue!$B$2:$B$24,MATCH(E12,Catalogue!$A$2:$A$24,0))) | H12: =D12-G12 | I12: =B12+E12 | J12: =I12*Paramètres!$B$3*(1-Paramètres!$B$4) | K12: =K11+C12
A13: 12 | B13: =I12 | C13: =B13*Paramètres!$B$3*(1-Paramètres!$B$4) | D13: =H12+C13 | E13: =IFERROR(MAXIFS(Catalogue!$A$2:$A$24,Catalogue!$B$2:$B$24,"<="&D13),0) | F13: =IF(E13=0,"—",INDEX(Catalogue!$C$2:$C$24,MATCH(E13,Catalogue!$A$2:$A$24,0))) | G13: =IF(E13=0,0,INDEX(Catalogue!$B$2:$B$24,MATCH(E13,Catalogue!$A$2:$A$24,0))) | H13: =D13-G13 | I13: =B13+E13 | J13: =I13*Paramètres!$B$3*(1-Paramètres!$B$4) | K13: =K12+C13
A14: 13 | B14: =I13 | C14: =B14*Paramètres!$B$3*(1-Paramètres!$B$4) | D14: =H13+C14 | E14: =IFERROR(MAXIFS(Catalogue!$A$2:$A$24,Catalogue!$B$2:$B$24,"<="&D14),0) | F14: =IF(E14=0,"—",INDEX(Catalogue!$C$2:$C$24,MATCH(E14,Catalogue!$A$2:$A$24,0))) | G14: =IF(E14=0,0,INDEX(Catalogue!$B$2:$B$24,MATCH(E14,Catalogue!$A$2:$A$24,0))) | H14: =D14-G14 | I14: =B14+E14 | J14: =I14*Paramètres!$B$3*(1-Paramètres!$B$4) | K14: =K13+C14
... A73: 72 | B73: =I72 | C73: =B73*Paramètres!$B$3*(1-Paramètres!$B$4) | D73: =H72+C73 | E73: =IFERROR(MAXIFS(Catalogue!$A$2:$A$24,Catalogue!$B$2:$B$24,"<="&D73),0) | F73: =IF(E73=0,"—",INDEX(Catalogue!$C$2:$C$24,MATCH(E73,Catalogue!$A$2:$A$24,0))) | G73: =IF(E73=0,0,INDEX(Catalogue!$B$2:$B$24,MATCH(E73,Catalogue!$A$2:$A$24,0))) | H73: =D73-G73 | I73: =B73+E73 | J73: =I73*Paramètres!$B$3*(1-Paramètres!$B$4) | K73: =K72+C73

Sheet Graphiques
A1: Graphiques (se redessinent avec les paramètres)
