Workbook

Sheet Lisez-moi
A1: Plan de scaling PropFirmMatch — avec temps de validation des étapes
A3: Pour Google Sheets : Fichier > Importer. Cellules bleues (Paramètres) modifiables ; les montants se recalculent.
A5: VOTRE MÉTHODE + TEMPS DE VALIDATION
A6: 01 octobre 2026 : compte direct FundedNext 10 000 $. Fin octobre, payout 10 % = 1 000 $, moins 30 % = 700 $.
A7: Chaque mois, tout l'argent disponible achète le maximum de firmes (chacune une fois).
A8: ORDRE D'ACHAT : d'abord tous les comptes DIRECTS / INSTANT, puis tous les 1 étape, puis les 2 étapes, puis les 3 étapes, puis les 4 étapes et plus. Au sein de chaque type : d'abord le cycle CFD (MetaTrader 5 en premier, puis les autres plateformes), ensuite le cycle Futures. À prix égal de rang, le plus gros capital est pris en premier.
A9: Comptes DIRECTS / INSTANT : financés immédiatement, ils rapportent dès la fin du mois d'achat.
A10: Comptes À ÉTAPES : il faut d'abord valider l'évaluation, à raison de 10 % par mois. Un objectif de 10 % prend 1 mois, 5 % prend une demi-mois. Un 2 étapes 10 %+5 % met donc 1,5 mois à être financé, et ne rapporte qu'ensuite. La durée exacte est dans l'onglet Détail (colonne Durée d'évaluation) et sa date de financement.
A11: Ce classeur ne contient QUE les firmes listées sur le site PropFirmMatch.
A12: Dans ce scénario (10 % / 30 %), la dernière firme est financée vers le 01 avril 2027.
A14: LES ONGLETS
A15: Plan mensuel : date en lettres, firmes achetées, capital financé (déjà validé), capital en cours d'évaluation, payout brut, part firme, salaire net, trésorerie.
... A20: Ordre et calendrier calculés pour 10 %/30 %. Colonnes d'argent en formules. Prix hors codes promo. Borne théorique sans échec d'évaluation ni plafond de retrait.

Sheet Paramètres
A1: Paramètres
A3: Payout mensuel (%) | B3: 0.1
A4: Part de la firme (%) | B4: 0.3
A5: Capital de départ ($) | B5: 10000

Sheet Plan mensuel
A1: Date | B1: Firmes achetées ce mois | C1: Nombre | D1: Capital financé (validé) ($) | E1: Capital en évaluation ($) | F1: Payout brut ($) | G1: Part firme ($) | H1: Salaire net ($) | I1: Trésorerie ($) | J1: Comptes financés | K1: Comptes au total
A2: 01 octobre 2026 | B2: FundedNext (compte de départ) | C2: 1 | D2: 10000 | E2: 0 | F2: =D2*Paramètres!$B$3 | G2: =F2*Paramètres!$B$4 | H2: =F2-G2 | I2: =H2-0 | J2: 1 | K2: 1
A3: 01 novembre 2026 | B3: Real Trader Fund | C3: 1 | D3: 110000 | E3: 0 | F3: =D3*Paramètres!$B$3 | G3: =F3*Paramètres!$B$4 | H3: =F3-G3 | I3: =I2+H3-360 | J3: 2 | K3: 2
A4: 01 décembre 2026 | B4: XPIPS; Funding Pips; Alpine Funded; FX2 Funding; Ifunds | C4: 5 | D4: 1210000 | E4: 0 | F4: =D4*Paramètres!$B$3 | G4: =F4*Paramètres!$B$4 | H4: =F4-G4 | I4: =I3+H4-5522 | J4: 7 | K4: 7
A5: 01 janvier 2027 | B5: ADN Broker; FundedHive; FundedForge; BuoyTrade; PaidPex; Lux Trading Firm … (+20) | C5: 26 | D5: 5850000 | E5: 17340000 | F5: =D5*Paramètres!$B$3 | G5: =F5*Paramètres!$B$4 | H5: =F5-G5 | I5: =I4+H5-121739 | J5: 15 | K5: 33
A6: 01 février 2027 | B6: PipFarm; Get Funded Now; Tradeify; BluSky; The Trading Pit Futures; Bulenox … (+47) | C6: 53 | D6: 29590000 | E6: 21038000 | F6: =D6*Paramètres!$B$3 | G6: =F6*Paramètres!$B$4 | H6: =F6-G6 | I6: =I5+H6-144314 | J6: 36 | K6: 86
A7: 01 mars 2027 | C7: 0 | D7: 48208000 | E7: 2420000 | F7: =D7*Paramètres!$B$3 | G7: =F7*Paramètres!$B$4 | H7: =F7-G7 | I7: =I6+H7-0 | J7: 81 | K7: 86
A8: 01 avril 2027 | C8: 0 | D8: 50628000 | E8: 0 | F8: =D8*Paramètres!$B$3 | G8: =F8*Paramètres!$B$4 | H8: =F8-G8 | I8: =I7+H8-0 | J8: 86 | K8: 86

Sheet Détail des achats
A1: Date d'achat | B1: Cycle | C1: Prop firm | D1: Plateforme | E1: MT5 ? | F1: Type | G1: Durée évaluation (mois) | H1: Date de financement | I1: Capital ($) | J1: Prix ($)
A2: 01 novembre 2026 | B2: CFD | C2: Real Trader Fund | D2: MT5 | E2: Oui | F2: Instant | G2: 0 | H2: 01 novembre 2026 | I2: 100000 | J2: 360
A3: 01 décembre 2026 | B3: CFD | C3: XPIPS | D3: MetaTrader 5 | E3: Oui | F3: Instant | G3: 0 | H3: 01 décembre 2026 | I3: 400000 | J3: 1596
A4: 01 décembre 2026 | B4: CFD | C4: Funding Pips | D4: cTrader, Match-Trader | E4: Oui | F4: Instant | G4: 0 | H4: 01 décembre 2026 | I4: 300000 | J4: 1332
A5: 01 décembre 2026 | B5: CFD | C5: Alpine Funded | D5: MetaTrader 5, cTrader | E5: Oui | F5: Instant | G5: 0 | H5: 01 décembre 2026 | I5: 200000 | J5: 839
A6: 01 décembre 2026 | B6: CFD | C6: FX2 Funding | D6: cTrader, DXtrade | E6: Oui | F6: Instant | G6: 0 | H6: 01 décembre 2026 | I6: 190000 | J6: 1055
A7: 01 décembre 2026 | B7: CFD | C7: Ifunds | D7: MetaTrader 5 | E7: Oui | F7: Instant | G7: 0 | H7: 01 décembre 2026 | I7: 10000 | J7: 700
A8: 01 janvier 2027 | B8: CFD | C8: ADN Broker | D8: MT5 | E8: Oui | F8: Instant | G8: 0 | H8: 01 janvier 2027 | I8: 500000 | J8: 50000
A9: 01 janvier 2027 | B9: CFD | C9: FundedHive | D9: cTrader | E9: Non | F9: Instant | G9: 0 | H9: 01 janvier 2027 | I9: 1000000 | J9: 349
A10: 01 janvier 2027 | B10: CFD | C10: FundedForge | D10: cTrader, Match-Trader, DXtrade | E10: Non | F10: Instant | G10: 0 | H10: 01 janvier 2027 | I10: 100000 | J10: 650
A11: 01 janvier 2027 | B11: CFD | C11: BuoyTrade | D11: MetaTrader | E11: Non | F11: Instant | G11: 0 | H11: 01 janvier 2027 | I11: 40000 | J11: 1980
A12: 01 janvier 2027 | B12: CFD | C12: PaidPex | D12: cTrader | E12: Oui | F12: 1 étape | G12: 1 | H12: 01 février 2027 | I12: 6000000 | J12: 11960
A13: 01 janvier 2027 | B13: CFD | C13: Lux Trading Firm | D13: TradingView | E13: Oui | F13: 1 étape | G13: 1 | H13: 01 février 2027 | I13: 5000000 | J13: 4995
... A86: 01 février 2027 | B86: CFD | C86: Turbo Trade Fund | D86: Match-Trader | E86: Non | F86: 3 étapes | G86: 1.5 | H86: 16 mars 2027 | I86: 200000 | J86: 799

Sheet Graphiques
A1: Graphiques
