Workbook

Sheet Lisez-moi
A1: Plan boule de neige — prop firms (bot 100 % automatique)
A3: Fichier conçu pour Google Sheets : Fichier > Importer > Importer les données. Toutes les cellules bleues de l'onglet Paramètres sont modifiables ; la Simulation et les Graphiques se recalculent automatiquement.
A5: ONGLETS
A6: Paramètres : rendement mensuel, capital de départ, part réinvestie, part trader par défaut.
A7: Données : la liste ordonnée des firmes à acheter — cycle CFD d'abord puis Futures, plans instant d'abord, du moins cher au plus cher. Capital cumulable max et prix de la composition la moins chère par firme.
A8: Simulation : un mois par ligne. Capital actif, profit brut, salaire net (après part firme), réinvesti, capital financé, répartition CFD / Futures, salaire net cumulé, trésorerie.
A9: Graphiques : capital financé, salaire mensuel brut et net, salaire net cumulé.
A11: MODÈLE
A12: Chaque mois : profit brut = capital financé × rendement. Salaire net = profit × part trader de chaque firme. Le salaire net réinvesti s'accumule et achète les firmes dans l'ordre de l'onglet Données, dès que la trésorerie suffit.
A13: Le nombre de firmes détenues chaque mois = nombre de firmes dont le prix cumulé est couvert par l'investi cumulé. Le capital financé en découle.
A15: LIMITES
A16: Borne théorique sous rendement constant, sans échec d'évaluation, drawdown, délai de payout ni plafond de retrait. Prix hors codes promo, à vérifier avant achat.

Sheet Paramètres
A1: Plan boule de neige — Paramètres
A3: Rendement mensuel brut du bot | B3: 0.1
A4: Capital de départ (FundedNext) | B4: 10000
A5: Part des gains réinvestie | B5: 1
A6: Part trader par défaut (si firme inconnue) | B6: 0.8
A7: Comptes achetés au maximum par mois | B7: 5
A9: Cellules bleues = à modifier. Tout le reste se recalcule (onglet Simulation).
A10: Modèle : départ FundedNext. Chaque mois profit = capital × rendement ; salaire net = profit × part trader.
A11: Le salaire net réinvesti achète les firmes dans l'ordre de l'onglet Données (CFD d'abord, instant d'abord, moins cher d'abord).

Sheet Données
A1: Ordre | B1: Cycle | C1: Prop firm | D1: Plan | E1: Capital ($) | F1: Prix ($) | G1: Part trader | H1: Capital × part | I1: Capital cumulé | J1: Capital×part cumulé | K1: Prix cumulé
A2: 1 | B2: CFD | C2: FundedHive | D2: Instant | E2: 1000000 | F2: 349 | G2: 0.99 | H2: =E2*G2 | I2: =E2 | J2: =H2 | K2: =F2
A3: 2 | B3: CFD | C3: Real Trader Fund | D3: Instant | E3: 100000 | F3: 360 | G3: 0.9 | H3: =E3*G3 | I3: =I2+E3 | J3: =J2+H3 | K3: =K2+F3
A4: 3 | B4: CFD | C4: Hydra Futures | D4: Instant | E4: 500000 | F4: 1980 | G4: 0.9 | H4: =E4*G4 | I4: =I3+E4 | J4: =J3+H4 | K4: =K3+F4
A5: 4 | B5: CFD | C5: XPIPS | D5: Instant | E5: 400000 | F5: 1596 | G5: 1 | H5: =E5*G5 | I5: =I4+E5 | J5: =J4+H5 | K5: =K4+F5
A6: 5 | B6: CFD | C6: Elysium Forex | D6: Instant | E6: 1000000 | F6: 4000 | G6: 0.9 | H6: =E6*G6 | I6: =I5+E6 | J6: =J5+H6 | K6: =K5+F6
A7: 6 | B7: CFD | C7: Alpine Funded | D7: Instant | E7: 200000 | F7: 839 | G7: 1 | H7: =E7*G7 | I7: =I6+E7 | J7: =J6+H7 | K7: =K6+F7
A8: 7 | B8: CFD | C8: Funding Pips | D8: Instant | E8: 300000 | F8: 1332 | G8: 1 | H8: =E8*G8 | I8: =I7+E8 | J8: =J7+H8 | K8: =K7+F8
A9: 8 | B9: CFD | C9: Hex Funded | D9: Instant | E9: 400000 | F9: 1908 | G9: 0.9 | H9: =E9*G9 | I9: =I8+E9 | J9: =J8+H9 | K9: =K8+F9
A10: 9 | B10: CFD | C10: FX2 Funding | D10: Instant | E10: 190000 | F10: 1055 | G10: 0.95 | H10: =E10*G10 | I10: =I9+E10 | J10: =J9+H10 | K10: =K9+F10
A11: 10 | B11: CFD | C11: Audacity Capital (FTP Instant Funding) | D11: Instant | E11: 240000 | F11: 1365 | G11: 0.8 | H11: =E11*G11 | I11: =I10+E11 | J11: =J10+H11 | K11: =K10+F11
A12: 11 | B12: CFD | C12: FundedForge | D12: Instant | E12: 100000 | F12: 650 | G12: 0.9 | H12: =E12*G12 | I12: =I11+E12 | J12: =J11+H12 | K12: =K11+F12
A13: 12 | B13: CFD | C13: We Copy Trade | D13: Instant | E13: 200000 | F13: 2000 | G13: 0.9 | H13: =E13*G13 | I13: =I12+E13 | J13: =J12+H13 | K13: =K12+F13
A14: 13 | B14: CFD | C14: BuoyTrade | D14: Instant | E14: 40000 | F14: 1980 | G14: 0.8 | H14: =E14*G14 | I14: =I13+E14 | J14: =J13+H14 | K14: =K13+F14
... A190: 189 | B190: Futures | C190: HyroTrader | D190: 2 étapes | E190: 200000 | F190: 999 | G190: 0.9 | H190: =E190*G190 | I190: =I189+E190 | J190: =J189+H190 | K190: =K189+F190

Sheet Simulation
A1: Mois | B1: Firmes au début | C1: Capital actif ($) | D1: Profit brut ($) | E1: Salaire net ($) | F1: Réinvesti ($) | G1: Investi cumulé ($) | H1: Firmes à la fin | I1: Capital financé ($) | J1: CFD ($) | K1: Futures ($) | L1: Salaire net cumulé ($) | M1: Trésorerie ($)
A2: 1 | B2: =IF(1=1,0,H1) | C2: =Paramètres!$B$4+IFERROR(INDEX(Données!$I$2:$I$190,$B2),0) | D2: =C2*Paramètres!$B$3 | E2: =(Paramètres!$B$4*Paramètres!$B$6+IFERROR(INDEX(Données!$J$2:$J$190,$B2),0))*Paramètres!$B$3 | F2: =E2*Paramètres!$B$5 | G2: =IF(1=1,F2,G1+F2) | H2: =MIN(189,$B2+Paramètres!$B$7,COUNTIF(Données!$K$2:$K$190,"<="&G2)) | I2: =Paramètres!$B$4+IFERROR(INDEX(Données!$I$2:$I$190,$H2),0) | J2: =Paramètres!$B$4+IFERROR(INDEX(Données!$I$2:$I$190,MIN($H2,160)),0) | K2: =I2-J2 | L2: =IF(1=1,E2,L1+E2) | M2: =G2-IFERROR(INDEX(Données!$K$2:$K$190,$H2),0)
A3: 2 | B3: =IF(2=1,0,H2) | C3: =Paramètres!$B$4+IFERROR(INDEX(Données!$I$2:$I$190,$B3),0) | D3: =C3*Paramètres!$B$3 | E3: =(Paramètres!$B$4*Paramètres!$B$6+IFERROR(INDEX(Données!$J$2:$J$190,$B3),0))*Paramètres!$B$3 | F3: =E3*Paramètres!$B$5 | G3: =IF(2=1,F3,G2+F3) | H3: =MIN(189,$B3+Paramètres!$B$7,COUNTIF(Données!$K$2:$K$190,"<="&G3)) | I3: =Paramètres!$B$4+IFERROR(INDEX(Données!$I$2:$I$190,$H3),0) | J3: =Paramètres!$B$4+IFERROR(INDEX(Données!$I$2:$I$190,MIN($H3,160)),0) | K3: =I3-J3 | L3: =IF(2=1,E3,L2+E3) | M3: =G3-IFERROR(INDEX(Données!$K$2:$K$190,$H3),0)
A4: 3 | B4: =IF(3=1,0,H3) | C4: =Paramètres!$B$4+IFERROR(INDEX(Données!$I$2:$I$190,$B4),0) | D4: =C4*Paramètres!$B$3 | E4: =(Paramètres!$B$4*Paramètres!$B$6+IFERROR(INDEX(Données!$J$2:$J$190,$B4),0))*Paramètres!$B$3 | F4: =E4*Paramètres!$B$5 | G4: =IF(3=1,F4,G3+F4) | H4: =MIN(189,$B4+Paramètres!$B$7,COUNTIF(Données!$K$2:$K$190,"<="&G4)) | I4: =Paramètres!$B$4+IFERROR(INDEX(Données!$I$2:$I$190,$H4),0) | J4: =Paramètres!$B$4+IFERROR(INDEX(Données!$I$2:$I$190,MIN($H4,160)),0) | K4: =I4-J4 | L4: =IF(3=1,E4,L3+E4) | M4: =G4-IFERROR(INDEX(Données!$K$2:$K$190,$H4),0)
A5: 4 | B5: =IF(4=1,0,H4) | C5: =Paramètres!$B$4+IFERROR(INDEX(Données!$I$2:$I$190,$B5),0) | D5: =C5*Paramètres!$B$3 | E5: =(Paramètres!$B$4*Paramètres!$B$6+IFERROR(INDEX(Données!$J$2:$J$190,$B5),0))*Paramètres!$B$3 | F5: =E5*Paramètres!$B$5 | G5: =IF(4=1,F5,G4+F5) | H5: =MIN(189,$B5+Paramètres!$B$7,COUNTIF(Données!$K$2:$K$190,"<="&G5)) | I5: =Paramètres!$B$4+IFERROR(INDEX(Données!$I$2:$I$190,$H5),0) | J5: =Paramètres!$B$4+IFERROR(INDEX(Données!$I$2:$I$190,MIN($H5,160)),0) | K5: =I5-J5 | L5: =IF(4=1,E5,L4+E5) | M5: =G5-IFERROR(INDEX(Données!$K$2:$K$190,$H5),0)
A6: 5 | B6: =IF(5=1,0,H5) | C6: =Paramètres!$B$4+IFERROR(INDEX(Données!$I$2:$I$190,$B6),0) | D6: =C6*Paramètres!$B$3 | E6: =(Paramètres!$B$4*Paramètres!$B$6+IFERROR(INDEX(Données!$J$2:$J$190,$B6),0))*Paramètres!$B$3 | F6: =E6*Paramètres!$B$5 | G6: =IF(5=1,F6,G5+F6) | H6: =MIN(189,$B6+Paramètres!$B$7,COUNTIF(Données!$K$2:$K$190,"<="&G6)) | I6: =Paramètres!$B$4+IFERROR(INDEX(Données!$I$2:$I$190,$H6),0) | J6: =Paramètres!$B$4+IFERROR(INDEX(Données!$I$2:$I$190,MIN($H6,160)),0) | K6: =I6-J6 | L6: =IF(5=1,E6,L5+E6) | M6: =G6-IFERROR(INDEX(Données!$K$2:$K$190,$H6),0)
A7: 6 | B7: =IF(6=1,0,H6) | C7: =Paramètres!$B$4+IFERROR(INDEX(Données!$I$2:$I$190,$B7),0) | D7: =C7*Paramètres!$B$3 | E7: =(Paramètres!$B$4*Paramètres!$B$6+IFERROR(INDEX(Données!$J$2:$J$190,$B7),0))*Paramètres!$B$3 | F7: =E7*Paramètres!$B$5 | G7: =IF(6=1,F7,G6+F7) | H7: =MIN(189,$B7+Paramètres!$B$7,COUNTIF(Données!$K$2:$K$190,"<="&G7)) | I7: =Paramètres!$B$4+IFERROR(INDEX(Données!$I$2:$I$190,$H7),0) | J7: =Paramètres!$B$4+IFERROR(INDEX(Données!$I$2:$I$190,MIN($H7,160)),0) | K7: =I7-J7 | L7: =IF(6=1,E7,L6+E7) | M7: =G7-IFERROR(INDEX(Données!$K$2:$K$190,$H7),0)
A8: 7 | B8: =IF(7=1,0,H7) | C8: =Paramètres!$B$4+IFERROR(INDEX(Données!$I$2:$I$190,$B8),0) | D8: =C8*Paramètres!$B$3 | E8: =(Paramètres!$B$4*Paramètres!$B$6+IFERROR(INDEX(Données!$J$2:$J$190,$B8),0))*Paramètres!$B$3 | F8: =E8*Paramètres!$B$5 | G8: =IF(7=1,F8,G7+F8) | H8: =MIN(189,$B8+Paramètres!$B$7,COUNTIF(Données!$K$2:$K$190,"<="&G8)) | I8: =Paramètres!$B$4+IFERROR(INDEX(Données!$I$2:$I$190,$H8),0) | J8: =Paramètres!$B$4+IFERROR(INDEX(Données!$I$2:$I$190,MIN($H8,160)),0) | K8: =I8-J8 | L8: =IF(7=1,E8,L7+E8) | M8: =G8-IFERROR(INDEX(Données!$K$2:$K$190,$H8),0)
A9: 8 | B9: =IF(8=1,0,H8) | C9: =Paramètres!$B$4+IFERROR(INDEX(Données!$I$2:$I$190,$B9),0) | D9: =C9*Paramètres!$B$3 | E9: =(Paramètres!$B$4*Paramètres!$B$6+IFERROR(INDEX(Données!$J$2:$J$190,$B9),0))*Paramètres!$B$3 | F9: =E9*Paramètres!$B$5 | G9: =IF(8=1,F9,G8+F9) | H9: =MIN(189,$B9+Paramètres!$B$7,COUNTIF(Données!$K$2:$K$190,"<="&G9)) | I9: =Paramètres!$B$4+IFERROR(INDEX(Données!$I$2:$I$190,$H9),0) | J9: =Paramètres!$B$4+IFERROR(INDEX(Données!$I$2:$I$190,MIN($H9,160)),0) | K9: =I9-J9 | L9: =IF(8=1,E9,L8+E9) | M9: =G9-IFERROR(INDEX(Données!$K$2:$K$190,$H9),0)
A10: 9 | B10: =IF(9=1,0,H9) | C10: =Paramètres!$B$4+IFERROR(INDEX(Données!$I$2:$I$190,$B10),0) | D10: =C10*Paramètres!$B$3 | E10: =(Paramètres!$B$4*Paramètres!$B$6+IFERROR(INDEX(Données!$J$2:$J$190,$B10),0))*Paramètres!$B$3 | F10: =E10*Paramètres!$B$5 | G10: =IF(9=1,F10,G9+F10) | H10: =MIN(189,$B10+Paramètres!$B$7,COUNTIF(Données!$K$2:$K$190,"<="&G10)) | I10: =Paramètres!$B$4+IFERROR(INDEX(Données!$I$2:$I$190,$H10),0) | J10: =Paramètres!$B$4+IFERROR(INDEX(Données!$I$2:$I$190,MIN($H10,160)),0) | K10: =I10-J10 | L10: =IF(9=1,E10,L9+E10) | M10: =G10-IFERROR(INDEX(Données!$K$2:$K$190,$H10),0)
A11: 10 | B11: =IF(10=1,0,H10) | C11: =Paramètres!$B$4+IFERROR(INDEX(Données!$I$2:$I$190,$B11),0) | D11: =C11*Paramètres!$B$3 | E11: =(Paramètres!$B$4*Paramètres!$B$6+IFERROR(INDEX(Données!$J$2:$J$190,$B11),0))*Paramètres!$B$3 | F11: =E11*Paramètres!$B$5 | G11: =IF(10=1,F11,G10+F11) | H11: =MIN(189,$B11+Paramètres!$B$7,COUNTIF(Données!$K$2:$K$190,"<="&G11)) | I11: =Paramètres!$B$4+IFERROR(INDEX(Données!$I$2:$I$190,$H11),0) | J11: =Paramètres!$B$4+IFERROR(INDEX(Données!$I$2:$I$190,MIN($H11,160)),0) | K11: =I11-J11 | L11: =IF(10=1,E11,L10+E11) | M11: =G11-IFERROR(INDEX(Données!$K$2:$K$190,$H11),0)
A12: 11 | B12: =IF(11=1,0,H11) | C12: =Paramètres!$B$4+IFERROR(INDEX(Données!$I$2:$I$190,$B12),0) | D12: =C12*Paramètres!$B$3 | E12: =(Paramètres!$B$4*Paramètres!$B$6+IFERROR(INDEX(Données!$J$2:$J$190,$B12),0))*Paramètres!$B$3 | F12: =E12*Paramètres!$B$5 | G12: =IF(11=1,F12,G11+F12) | H12: =MIN(189,$B12+Paramètres!$B$7,COUNTIF(Données!$K$2:$K$190,"<="&G12)) | I12: =Paramètres!$B$4+IFERROR(INDEX(Données!$I$2:$I$190,$H12),0) | J12: =Paramètres!$B$4+IFERROR(INDEX(Données!$I$2:$I$190,MIN($H12,160)),0) | K12: =I12-J12 | L12: =IF(11=1,E12,L11+E12) | M12: =G12-IFERROR(INDEX(Données!$K$2:$K$190,$H12),0)
A13: 12 | B13: =IF(12=1,0,H12) | C13: =Paramètres!$B$4+IFERROR(INDEX(Données!$I$2:$I$190,$B13),0) | D13: =C13*Paramètres!$B$3 | E13: =(Paramètres!$B$4*Paramètres!$B$6+IFERROR(INDEX(Données!$J$2:$J$190,$B13),0))*Paramètres!$B$3 | F13: =E13*Paramètres!$B$5 | G13: =IF(12=1,F13,G12+F13) | H13: =MIN(189,$B13+Paramètres!$B$7,COUNTIF(Données!$K$2:$K$190,"<="&G13)) | I13: =Paramètres!$B$4+IFERROR(INDEX(Données!$I$2:$I$190,$H13),0) | J13: =Paramètres!$B$4+IFERROR(INDEX(Données!$I$2:$I$190,MIN($H13,160)),0) | K13: =I13-J13 | L13: =IF(12=1,E13,L12+E13) | M13: =G13-IFERROR(INDEX(Données!$K$2:$K$190,$H13),0)
A14: 13 | B14: =IF(13=1,0,H13) | C14: =Paramètres!$B$4+IFERROR(INDEX(Données!$I$2:$I$190,$B14),0) | D14: =C14*Paramètres!$B$3 | E14: =(Paramètres!$B$4*Paramètres!$B$6+IFERROR(INDEX(Données!$J$2:$J$190,$B14),0))*Paramètres!$B$3 | F14: =E14*Paramètres!$B$5 | G14: =IF(13=1,F14,G13+F14) | H14: =MIN(189,$B14+Paramètres!$B$7,COUNTIF(Données!$K$2:$K$190,"<="&G14)) | I14: =Paramètres!$B$4+IFERROR(INDEX(Données!$I$2:$I$190,$H14),0) | J14: =Paramètres!$B$4+IFERROR(INDEX(Données!$I$2:$I$190,MIN($H14,160)),0) | K14: =I14-J14 | L14: =IF(13=1,E14,L13+E14) | M14: =G14-IFERROR(INDEX(Données!$K$2:$K$190,$H14),0)
A15: 14 | B15: =IF(14=1,0,H14) | C15: =Paramètres!$B$4+IFERROR(INDEX(Données!$I$2:$I$190,$B15),0) | D15: =C15*Paramètres!$B$3 | E15: =(Paramètres!$B$4*Paramètres!$B$6+IFERROR(INDEX(Données!$J$2:$J$190,$B15),0))*Paramètres!$B$3 | F15: =E15*Paramètres!$B$5 | G15: =IF(14=1,F15,G14+F15) | H15: =MIN(189,$B15+Paramètres!$B$7,COUNTIF(Données!$K$2:$K$190,"<="&G15)) | I15: =Paramètres!$B$4+IFERROR(INDEX(Données!$I$2:$I$190,$H15),0) | J15: =Paramètres!$B$4+IFERROR(INDEX(Données!$I$2:$I$190,MIN($H15,160)),0) | K15: =I15-J15 | L15: =IF(14=1,E15,L14+E15) | M15: =G15-IFERROR(INDEX(Données!$K$2:$K$190,$H15),0)
A16: 15 | B16: =IF(15=1,0,H15) | C16: =Paramètres!$B$4+IFERROR(INDEX(Données!$I$2:$I$190,$B16),0) | D16: =C16*Paramètres!$B$3 | E16: =(Paramètres!$B$4*Paramètres!$B$6+IFERROR(INDEX(Données!$J$2:$J$190,$B16),0))*Paramètres!$B$3 | F16: =E16*Paramètres!$B$5 | G16: =IF(15=1,F16,G15+F16) | H16: =MIN(189,$B16+Paramètres!$B$7,COUNTIF(Données!$K$2:$K$190,"<="&G16)) | I16: =Paramètres!$B$4+IFERROR(INDEX(Données!$I$2:$I$190,$H16),0) | J16: =Paramètres!$B$4+IFERROR(INDEX(Données!$I$2:$I$190,MIN($H16,160)),0) | K16: =I16-J16 | L16: =IF(15=1,E16,L15+E16) | M16: =G16-IFERROR(INDEX(Données!$K$2:$K$190,$H16),0)
A17: 16 | B17: =IF(16=1,0,H16) | C17: =Paramètres!$B$4+IFERROR(INDEX(Données!$I$2:$I$190,$B17),0) | D17: =C17*Paramètres!$B$3 | E17: =(Paramètres!$B$4*Paramètres!$B$6+IFERROR(INDEX(Données!$J$2:$J$190,$B17),0))*Paramètres!$B$3 | F17: =E17*Paramètres!$B$5 | G17: =IF(16=1,F17,G16+F17) | H17: =MIN(189,$B17+Paramètres!$B$7,COUNTIF(Données!$K$2:$K$190,"<="&G17)) | I17: =Paramètres!$B$4+IFERROR(INDEX(Données!$I$2:$I$190,$H17),0) | J17: =Paramètres!$B$4+IFERROR(INDEX(Données!$I$2:$I$190,MIN($H17,160)),0) | K17: =I17-J17 | L17: =IF(16=1,E17,L16+E17) | M17: =G17-IFERROR(INDEX(Données!$K$2:$K$190,$H17),0)
A18: 17 | B18: =IF(17=1,0,H17) | C18: =Paramètres!$B$4+IFERROR(INDEX(Données!$I$2:$I$190,$B18),0) | D18: =C18*Paramètres!$B$3 | E18: =(Paramètres!$B$4*Paramètres!$B$6+IFERROR(INDEX(Données!$J$2:$J$190,$B18),0))*Paramètres!$B$3 | F18: =E18*Paramètres!$B$5 | G18: =IF(17=1,F18,G17+F18) | H18: =MIN(189,$B18+Paramètres!$B$7,COUNTIF(Données!$K$2:$K$190,"<="&G18)) | I18: =Paramètres!$B$4+IFERROR(INDEX(Données!$I$2:$I$190,$H18),0) | J18: =Paramètres!$B$4+IFERROR(INDEX(Données!$I$2:$I$190,MIN($H18,160)),0) | K18: =I18-J18 | L18: =IF(17=1,E18,L17+E18) | M18: =G18-IFERROR(INDEX(Données!$K$2:$K$190,$H18),0)
A19: 18 | B19: =IF(18=1,0,H18) | C19: =Paramètres!$B$4+IFERROR(INDEX(Données!$I$2:$I$190,$B19),0) | D19: =C19*Paramètres!$B$3 | E19: =(Paramètres!$B$4*Paramètres!$B$6+IFERROR(INDEX(Données!$J$2:$J$190,$B19),0))*Paramètres!$B$3 | F19: =E19*Paramètres!$B$5 | G19: =IF(18=1,F19,G18+F19) | H19: =MIN(189,$B19+Paramètres!$B$7,COUNTIF(Données!$K$2:$K$190,"<="&G19)) | I19: =Paramètres!$B$4+IFERROR(INDEX(Données!$I$2:$I$190,$H19),0) | J19: =Paramètres!$B$4+IFERROR(INDEX(Données!$I$2:$I$190,MIN($H19,160)),0) | K19: =I19-J19 | L19: =IF(18=1,E19,L18+E19) | M19: =G19-IFERROR(INDEX(Données!$K$2:$K$190,$H19),0)
A20: 19 | B20: =IF(19=1,0,H19) | C20: =Paramètres!$B$4+IFERROR(INDEX(Données!$I$2:$I$190,$B20),0) | D20: =C20*Paramètres!$B$3 | E20: =(Paramètres!$B$4*Paramètres!$B$6+IFERROR(INDEX(Données!$J$2:$J$190,$B20),0))*Paramètres!$B$3 | F20: =E20*Paramètres!$B$5 | G20: =IF(19=1,F20,G19+F20) | H20: =MIN(189,$B20+Paramètres!$B$7,COUNTIF(Données!$K$2:$K$190,"<="&G20)) | I20: =Paramètres!$B$4+IFERROR(INDEX(Données!$I$2:$I$190,$H20),0) | J20: =Paramètres!$B$4+IFERROR(INDEX(Données!$I$2:$I$190,MIN($H20,160)),0) | K20: =I20-J20 | L20: =IF(19=1,E20,L19+E20) | M20: =G20-IFERROR(INDEX(Données!$K$2:$K$190,$H20),0)
A21: 20 | B21: =IF(20=1,0,H20) | C21: =Paramètres!$B$4+IFERROR(INDEX(Données!$I$2:$I$190,$B21),0) | D21: =C21*Paramètres!$B$3 | E21: =(Paramètres!$B$4*Paramètres!$B$6+IFERROR(INDEX(Données!$J$2:$J$190,$B21),0))*Paramètres!$B$3 | F21: =E21*Paramètres!$B$5 | G21: =IF(20=1,F21,G20+F21) | H21: =MIN(189,$B21+Paramètres!$B$7,COUNTIF(Données!$K$2:$K$190,"<="&G21)) | I21: =Paramètres!$B$4+IFERROR(INDEX(Données!$I$2:$I$190,$H21),0) | J21: =Paramètres!$B$4+IFERROR(INDEX(Données!$I$2:$I$190,MIN($H21,160)),0) | K21: =I21-J21 | L21: =IF(20=1,E21,L20+E21) | M21: =G21-IFERROR(INDEX(Données!$K$2:$K$190,$H21),0)
A22: 21 | B22: =IF(21=1,0,H21) | C22: =Paramètres!$B$4+IFERROR(INDEX(Données!$I$2:$I$190,$B22),0) | D22: =C22*Paramètres!$B$3 | E22: =(Paramètres!$B$4*Paramètres!$B$6+IFERROR(INDEX(Données!$J$2:$J$190,$B22),0))*Paramètres!$B$3 | F22: =E22*Paramètres!$B$5 | G22: =IF(21=1,F22,G21+F22) | H22: =MIN(189,$B22+Paramètres!$B$7,COUNTIF(Données!$K$2:$K$190,"<="&G22)) | I22: =Paramètres!$B$4+IFERROR(INDEX(Données!$I$2:$I$190,$H22),0) | J22: =Paramètres!$B$4+IFERROR(INDEX(Données!$I$2:$I$190,MIN($H22,160)),0) | K22: =I22-J22 | L22: =IF(21=1,E22,L21+E22) | M22: =G22-IFERROR(INDEX(Données!$K$2:$K$190,$H22),0)
A23: 22 | B23: =IF(22=1,0,H22) | C23: =Paramètres!$B$4+IFERROR(INDEX(Données!$I$2:$I$190,$B23),0) | D23: =C23*Paramètres!$B$3 | E23: =(Paramètres!$B$4*Paramètres!$B$6+IFERROR(INDEX(Données!$J$2:$J$190,$B23),0))*Paramètres!$B$3 | F23: =E23*Paramètres!$B$5 | G23: =IF(22=1,F23,G22+F23) | H23: =MIN(189,$B23+Paramètres!$B$7,COUNTIF(Données!$K$2:$K$190,"<="&G23)) | I23: =Paramètres!$B$4+IFERROR(INDEX(Données!$I$2:$I$190,$H23),0) | J23: =Paramètres!$B$4+IFERROR(INDEX(Données!$I$2:$I$190,MIN($H23,160)),0) | K23: =I23-J23 | L23: =IF(22=1,E23,L22+E23) | M23: =G23-IFERROR(INDEX(Données!$K$2:$K$190,$H23),0)
A24: 23 | B24: =IF(23=1,0,H23) | C24: =Paramètres!$B$4+IFERROR(INDEX(Données!$I$2:$I$190,$B24),0) | D24: =C24*Paramètres!$B$3 | E24: =(Paramètres!$B$4*Paramètres!$B$6+IFERROR(INDEX(Données!$J$2:$J$190,$B24),0))*Paramètres!$B$3 | F24: =E24*Paramètres!$B$5 | G24: =IF(23=1,F24,G23+F24) | H24: =MIN(189,$B24+Paramètres!$B$7,COUNTIF(Données!$K$2:$K$190,"<="&G24)) | I24: =Paramètres!$B$4+IFERROR(INDEX(Données!$I$2:$I$190,$H24),0) | J24: =Paramètres!$B$4+IFERROR(INDEX(Données!$I$2:$I$190,MIN($H24,160)),0) | K24: =I24-J24 | L24: =IF(23=1,E24,L23+E24) | M24: =G24-IFERROR(INDEX(Données!$K$2:$K$190,$H24),0)
A25: 24 | B25: =IF(24=1,0,H24) | C25: =Paramètres!$B$4+IFERROR(INDEX(Données!$I$2:$I$190,$B25),0) | D25: =C25*Paramètres!$B$3 | E25: =(Paramètres!$B$4*Paramètres!$B$6+IFERROR(INDEX(Données!$J$2:$J$190,$B25),0))*Paramètres!$B$3 | F25: =E25*Paramètres!$B$5 | G25: =IF(24=1,F25,G24+F25) | H25: =MIN(189,$B25+Paramètres!$B$7,COUNTIF(Données!$K$2:$K$190,"<="&G25)) | I25: =Paramètres!$B$4+IFERROR(INDEX(Données!$I$2:$I$190,$H25),0) | J25: =Paramètres!$B$4+IFERROR(INDEX(Données!$I$2:$I$190,MIN($H25,160)),0) | K25: =I25-J25 | L25: =IF(24=1,E25,L24+E25) | M25: =G25-IFERROR(INDEX(Données!$K$2:$K$190,$H25),0)
A26: 25 | B26: =IF(25=1,0,H25) | C26: =Paramètres!$B$4+IFERROR(INDEX(Données!$I$2:$I$190,$B26),0) | D26: =C26*Paramètres!$B$3 | E26: =(Paramètres!$B$4*Paramètres!$B$6+IFERROR(INDEX(Données!$J$2:$J$190,$B26),0))*Paramètres!$B$3 | F26: =E26*Paramètres!$B$5 | G26: =IF(25=1,F26,G25+F26) | H26: =MIN(189,$B26+Paramètres!$B$7,COUNTIF(Données!$K$2:$K$190,"<="&G26)) | I26: =Paramètres!$B$4+IFERROR(INDEX(Données!$I$2:$I$190,$H26),0) | J26: =Paramètres!$B$4+IFERROR(INDEX(Données!$I$2:$I$190,MIN($H26,160)),0) | K26: =I26-J26 | L26: =IF(25=1,E26,L25+E26) | M26: =G26-IFERROR(INDEX(Données!$K$2:$K$190,$H26),0)
A27: 26 | B27: =IF(26=1,0,H26) | C27: =Paramètres!$B$4+IFERROR(INDEX(Données!$I$2:$I$190,$B27),0) | D27: =C27*Paramètres!$B$3 | E27: =(Paramètres!$B$4*Paramètres!$B$6+IFERROR(INDEX(Données!$J$2:$J$190,$B27),0))*Paramètres!$B$3 | F27: =E27*Paramètres!$B$5 | G27: =IF(26=1,F27,G26+F27) | H27: =MIN(189,$B27+Paramètres!$B$7,COUNTIF(Données!$K$2:$K$190,"<="&G27)) | I27: =Paramètres!$B$4+IFERROR(INDEX(Données!$I$2:$I$190,$H27),0) | J27: =Paramètres!$B$4+IFERROR(INDEX(Données!$I$2:$I$190,MIN($H27,160)),0) | K27: =I27-J27 | L27: =IF(26=1,E27,L26+E27) | M27: =G27-IFERROR(INDEX(Données!$K$2:$K$190,$H27),0)
A28: 27 | B28: =IF(27=1,0,H27) | C28: =Paramètres!$B$4+IFERROR(INDEX(Données!$I$2:$I$190,$B28),0) | D28: =C28*Paramètres!$B$3 | E28: =(Paramètres!$B$4*Paramètres!$B$6+IFERROR(INDEX(Données!$J$2:$J$190,$B28),0))*Paramètres!$B$3 | F28: =E28*Paramètres!$B$5 | G28: =IF(27=1,F28,G27+F28) | H28: =MIN(189,$B28+Paramètres!$B$7,COUNTIF(Données!$K$2:$K$190,"<="&G28)) | I28: =Paramètres!$B$4+IFERROR(INDEX(Données!$I$2:$I$190,$H28),0) | J28: =Paramètres!$B$4+IFERROR(INDEX(Données!$I$2:$I$190,MIN($H28,160)),0) | K28: =I28-J28 | L28: =IF(27=1,E28,L27+E28) | M28: =G28-IFERROR(INDEX(Données!$K$2:$K$190,$H28),0)
A29: 28 | B29: =IF(28=1,0,H28) | C29: =Paramètres!$B$4+IFERROR(INDEX(Données!$I$2:$I$190,$B29),0) | D29: =C29*Paramètres!$B$3 | E29: =(Paramètres!$B$4*Paramètres!$B$6+IFERROR(INDEX(Données!$J$2:$J$190,$B29),0))*Paramètres!$B$3 | F29: =E29*Paramètres!$B$5 | G29: =IF(28=1,F29,G28+F29) | H29: =MIN(189,$B29+Paramètres!$B$7,COUNTIF(Données!$K$2:$K$190,"<="&G29)) | I29: =Paramètres!$B$4+IFERROR(INDEX(Données!$I$2:$I$190,$H29),0) | J29: =Paramètres!$B$4+IFERROR(INDEX(Données!$I$2:$I$190,MIN($H29,160)),0) | K29: =I29-J29 | L29: =IF(28=1,E29,L28+E29) | M29: =G29-IFERROR(INDEX(Données!$K$2:$K$190,$H29),0)
A30: 29 | B30: =IF(29=1,0,H29) | C30: =Paramètres!$B$4+IFERROR(INDEX(Données!$I$2:$I$190,$B30),0) | D30: =C30*Paramètres!$B$3 | E30: =(Paramètres!$B$4*Paramètres!$B$6+IFERROR(INDEX(Données!$J$2:$J$190,$B30),0))*Paramètres!$B$3 | F30: =E30*Paramètres!$B$5 | G30: =IF(29=1,F30,G29+F30) | H30: =MIN(189,$B30+Paramètres!$B$7,COUNTIF(Données!$K$2:$K$190,"<="&G30)) | I30: =Paramètres!$B$4+IFERROR(INDEX(Données!$I$2:$I$190,$H30),0) | J30: =Paramètres!$B$4+IFERROR(INDEX(Données!$I$2:$I$190,MIN($H30,160)),0) | K30: =I30-J30 | L30: =IF(29=1,E30,L29+E30) | M30: =G30-IFERROR(INDEX(Données!$K$2:$K$190,$H30),0)
A31: 30 | B31: =IF(30=1,0,H30) | C31: =Paramètres!$B$4+IFERROR(INDEX(Données!$I$2:$I$190,$B31),0) | D31: =C31*Paramètres!$B$3 | E31: =(Paramètres!$B$4*Paramètres!$B$6+IFERROR(INDEX(Données!$J$2:$J$190,$B31),0))*Paramètres!$B$3 | F31: =E31*Paramètres!$B$5 | G31: =IF(30=1,F31,G30+F31) | H31: =MIN(189,$B31+Paramètres!$B$7,COUNTIF(Données!$K$2:$K$190,"<="&G31)) | I31: =Paramètres!$B$4+IFERROR(INDEX(Données!$I$2:$I$190,$H31),0) | J31: =Paramètres!$B$4+IFERROR(INDEX(Données!$I$2:$I$190,MIN($H31,160)),0) | K31: =I31-J31 | L31: =IF(30=1,E31,L30+E31) | M31: =G31-IFERROR(INDEX(Données!$K$2:$K$190,$H31),0)
A32: 31 | B32: =IF(31=1,0,H31) | C32: =Paramètres!$B$4+IFERROR(INDEX(Données!$I$2:$I$190,$B32),0) | D32: =C32*Paramètres!$B$3 | E32: =(Paramètres!$B$4*Paramètres!$B$6+IFERROR(INDEX(Données!$J$2:$J$190,$B32),0))*Paramètres!$B$3 | F32: =E32*Paramètres!$B$5 | G32: =IF(31=1,F32,G31+F32) | H32: =MIN(189,$B32+Paramètres!$B$7,COUNTIF(Données!$K$2:$K$190,"<="&G32)) | I32: =Paramètres!$B$4+IFERROR(INDEX(Données!$I$2:$I$190,$H32),0) | J32: =Paramètres!$B$4+IFERROR(INDEX(Données!$I$2:$I$190,MIN($H32,160)),0) | K32: =I32-J32 | L32: =IF(31=1,E32,L31+E32) | M32: =G32-IFERROR(INDEX(Données!$K$2:$K$190,$H32),0)
A33: 32 | B33: =IF(32=1,0,H32) | C33: =Paramètres!$B$4+IFERROR(INDEX(Données!$I$2:$I$190,$B33),0) | D33: =C33*Paramètres!$B$3 | E33: =(Paramètres!$B$4*Paramètres!$B$6+IFERROR(INDEX(Données!$J$2:$J$190,$B33),0))*Paramètres!$B$3 | F33: =E33*Paramètres!$B$5 | G33: =IF(32=1,F33,G32+F33) | H33: =MIN(189,$B33+Paramètres!$B$7,COUNTIF(Données!$K$2:$K$190,"<="&G33)) | I33: =Paramètres!$B$4+IFERROR(INDEX(Données!$I$2:$I$190,$H33),0) | J33: =Paramètres!$B$4+IFERROR(INDEX(Données!$I$2:$I$190,MIN($H33,160)),0) | K33: =I33-J33 | L33: =IF(32=1,E33,L32+E33) | M33: =G33-IFERROR(INDEX(Données!$K$2:$K$190,$H33),0)
A34: 33 | B34: =IF(33=1,0,H33) | C34: =Paramètres!$B$4+IFERROR(INDEX(Données!$I$2:$I$190,$B34),0) | D34: =C34*Paramètres!$B$3 | E34: =(Paramètres!$B$4*Paramètres!$B$6+IFERROR(INDEX(Données!$J$2:$J$190,$B34),0))*Paramètres!$B$3 | F34: =E34*Paramètres!$B$5 | G34: =IF(33=1,F34,G33+F34) | H34: =MIN(189,$B34+Paramètres!$B$7,COUNTIF(Données!$K$2:$K$190,"<="&G34)) | I34: =Paramètres!$B$4+IFERROR(INDEX(Données!$I$2:$I$190,$H34),0) | J34: =Paramètres!$B$4+IFERROR(INDEX(Données!$I$2:$I$190,MIN($H34,160)),0) | K34: =I34-J34 | L34: =IF(33=1,E34,L33+E34) | M34: =G34-IFERROR(INDEX(Données!$K$2:$K$190,$H34),0)
A35: 34 | B35: =IF(34=1,0,H34) | C35: =Paramètres!$B$4+IFERROR(INDEX(Données!$I$2:$I$190,$B35),0) | D35: =C35*Paramètres!$B$3 | E35: =(Paramètres!$B$4*Paramètres!$B$6+IFERROR(INDEX(Données!$J$2:$J$190,$B35),0))*Paramètres!$B$3 | F35: =E35*Paramètres!$B$5 | G35: =IF(34=1,F35,G34+F35) | H35: =MIN(189,$B35+Paramètres!$B$7,COUNTIF(Données!$K$2:$K$190,"<="&G35)) | I35: =Paramètres!$B$4+IFERROR(INDEX(Données!$I$2:$I$190,$H35),0) | J35: =Paramètres!$B$4+IFERROR(INDEX(Données!$I$2:$I$190,MIN($H35,160)),0) | K35: =I35-J35 | L35: =IF(34=1,E35,L34+E35) | M35: =G35-IFERROR(INDEX(Données!$K$2:$K$190,$H35),0)
A36: 35 | B36: =IF(35=1,0,H35) | C36: =Paramètres!$B$4+IFERROR(INDEX(Données!$I$2:$I$190,$B36),0) | D36: =C36*Paramètres!$B$3 | E36: =(Paramètres!$B$4*Paramètres!$B$6+IFERROR(INDEX(Données!$J$2:$J$190,$B36),0))*Paramètres!$B$3 | F36: =E36*Paramètres!$B$5 | G36: =IF(35=1,F36,G35+F36) | H36: =MIN(189,$B36+Paramètres!$B$7,COUNTIF(Données!$K$2:$K$190,"<="&G36)) | I36: =Paramètres!$B$4+IFERROR(INDEX(Données!$I$2:$I$190,$H36),0) | J36: =Paramètres!$B$4+IFERROR(INDEX(Données!$I$2:$I$190,MIN($H36,160)),0) | K36: =I36-J36 | L36: =IF(35=1,E36,L35+E36) | M36: =G36-IFERROR(INDEX(Données!$K$2:$K$190,$H36),0)
A37: 36 | B37: =IF(36=1,0,H36) | C37: =Paramètres!$B$4+IFERROR(INDEX(Données!$I$2:$I$190,$B37),0) | D37: =C37*Paramètres!$B$3 | E37: =(Paramètres!$B$4*Paramètres!$B$6+IFERROR(INDEX(Données!$J$2:$J$190,$B37),0))*Paramètres!$B$3 | F37: =E37*Paramètres!$B$5 | G37: =IF(36=1,F37,G36+F37) | H37: =MIN(189,$B37+Paramètres!$B$7,COUNTIF(Données!$K$2:$K$190,"<="&G37)) | I37: =Paramètres!$B$4+IFERROR(INDEX(Données!$I$2:$I$190,$H37),0) | J37: =Paramètres!$B$4+IFERROR(INDEX(Données!$I$2:$I$190,MIN($H37,160)),0) | K37: =I37-J37 | L37: =IF(36=1,E37,L36+E37) | M37: =G37-IFERROR(INDEX(Données!$K$2:$K$190,$H37),0)
A38: 37 | B38: =IF(37=1,0,H37) | C38: =Paramètres!$B$4+IFERROR(INDEX(Données!$I$2:$I$190,$B38),0) | D38: =C38*Paramètres!$B$3 | E38: =(Paramètres!$B$4*Paramètres!$B$6+IFERROR(INDEX(Données!$J$2:$J$190,$B38),0))*Paramètres!$B$3 | F38: =E38*Paramètres!$B$5 | G38: =IF(37=1,F38,G37+F38) | H38: =MIN(189,$B38+Paramètres!$B$7,COUNTIF(Données!$K$2:$K$190,"<="&G38)) | I38: =Paramètres!$B$4+IFERROR(INDEX(Données!$I$2:$I$190,$H38),0) | J38: =Paramètres!$B$4+IFERROR(INDEX(Données!$I$2:$I$190,MIN($H38,160)),0) | K38: =I38-J38 | L38: =IF(37=1,E38,L37+E38) | M38: =G38-IFERROR(INDEX(Données!$K$2:$K$190,$H38),0)
A39: 38 | B39: =IF(38=1,0,H38) | C39: =Paramètres!$B$4+IFERROR(INDEX(Données!$I$2:$I$190,$B39),0) | D39: =C39*Paramètres!$B$3 | E39: =(Paramètres!$B$4*Paramètres!$B$6+IFERROR(INDEX(Données!$J$2:$J$190,$B39),0))*Paramètres!$B$3 | F39: =E39*Paramètres!$B$5 | G39: =IF(38=1,F39,G38+F39) | H39: =MIN(189,$B39+Paramètres!$B$7,COUNTIF(Données!$K$2:$K$190,"<="&G39)) | I39: =Paramètres!$B$4+IFERROR(INDEX(Données!$I$2:$I$190,$H39),0) | J39: =Paramètres!$B$4+IFERROR(INDEX(Données!$I$2:$I$190,MIN($H39,160)),0) | K39: =I39-J39 | L39: =IF(38=1,E39,L38+E39) | M39: =G39-IFERROR(INDEX(Données!$K$2:$K$190,$H39),0)
A40: 39 | B40: =IF(39=1,0,H39) | C40: =Paramètres!$B$4+IFERROR(INDEX(Données!$I$2:$I$190,$B40),0) | D40: =C40*Paramètres!$B$3 | E40: =(Paramètres!$B$4*Paramètres!$B$6+IFERROR(INDEX(Données!$J$2:$J$190,$B40),0))*Paramètres!$B$3 | F40: =E40*Paramètres!$B$5 | G40: =IF(39=1,F40,G39+F40) | H40: =MIN(189,$B40+Paramètres!$B$7,COUNTIF(Données!$K$2:$K$190,"<="&G40)) | I40: =Paramètres!$B$4+IFERROR(INDEX(Données!$I$2:$I$190,$H40),0) | J40: =Paramètres!$B$4+IFERROR(INDEX(Données!$I$2:$I$190,MIN($H40,160)),0) | K40: =I40-J40 | L40: =IF(39=1,E40,L39+E40) | M40: =G40-IFERROR(INDEX(Données!$K$2:$K$190,$H40),0)
A41: 40 | B41: =IF(40=1,0,H40) | C41: =Paramètres!$B$4+IFERROR(INDEX(Données!$I$2:$I$190,$B41),0) | D41: =C41*Paramètres!$B$3 | E41: =(Paramètres!$B$4*Paramètres!$B$6+IFERROR(INDEX(Données!$J$2:$J$190,$B41),0))*Paramètres!$B$3 | F41: =E41*Paramètres!$B$5 | G41: =IF(40=1,F41,G40+F41) | H41: =MIN(189,$B41+Paramètres!$B$7,COUNTIF(Données!$K$2:$K$190,"<="&G41)) | I41: =Paramètres!$B$4+IFERROR(INDEX(Données!$I$2:$I$190,$H41),0) | J41: =Paramètres!$B$4+IFERROR(INDEX(Données!$I$2:$I$190,MIN($H41,160)),0) | K41: =I41-J41 | L41: =IF(40=1,E41,L40+E41) | M41: =G41-IFERROR(INDEX(Données!$K$2:$K$190,$H41),0)
A42: 41 | B42: =IF(41=1,0,H41) | C42: =Paramètres!$B$4+IFERROR(INDEX(Données!$I$2:$I$190,$B42),0) | D42: =C42*Paramètres!$B$3 | E42: =(Paramètres!$B$4*Paramètres!$B$6+IFERROR(INDEX(Données!$J$2:$J$190,$B42),0))*Paramètres!$B$3 | F42: =E42*Paramètres!$B$5 | G42: =IF(41=1,F42,G41+F42) | H42: =MIN(189,$B42+Paramètres!$B$7,COUNTIF(Données!$K$2:$K$190,"<="&G42)) | I42: =Paramètres!$B$4+IFERROR(INDEX(Données!$I$2:$I$190,$H42),0) | J42: =Paramètres!$B$4+IFERROR(INDEX(Données!$I$2:$I$190,MIN($H42,160)),0) | K42: =I42-J42 | L42: =IF(41=1,E42,L41+E42) | M42: =G42-IFERROR(INDEX(Données!$K$2:$K$190,$H42),0)
A43: 42 | B43: =IF(42=1,0,H42) | C43: =Paramètres!$B$4+IFERROR(INDEX(Données!$I$2:$I$190,$B43),0) | D43: =C43*Paramètres!$B$3 | E43: =(Paramètres!$B$4*Paramètres!$B$6+IFERROR(INDEX(Données!$J$2:$J$190,$B43),0))*Paramètres!$B$3 | F43: =E43*Paramètres!$B$5 | G43: =IF(42=1,F43,G42+F43) | H43: =MIN(189,$B43+Paramètres!$B$7,COUNTIF(Données!$K$2:$K$190,"<="&G43)) | I43: =Paramètres!$B$4+IFERROR(INDEX(Données!$I$2:$I$190,$H43),0) | J43: =Paramètres!$B$4+IFERROR(INDEX(Données!$I$2:$I$190,MIN($H43,160)),0) | K43: =I43-J43 | L43: =IF(42=1,E43,L42+E43) | M43: =G43-IFERROR(INDEX(Données!$K$2:$K$190,$H43),0)
A44: 43 | B44: =IF(43=1,0,H43) | C44: =Paramètres!$B$4+IFERROR(INDEX(Données!$I$2:$I$190,$B44),0) | D44: =C44*Paramètres!$B$3 | E44: =(Paramètres!$B$4*Paramètres!$B$6+IFERROR(INDEX(Données!$J$2:$J$190,$B44),0))*Paramètres!$B$3 | F44: =E44*Paramètres!$B$5 | G44: =IF(43=1,F44,G43+F44) | H44: =MIN(189,$B44+Paramètres!$B$7,COUNTIF(Données!$K$2:$K$190,"<="&G44)) | I44: =Paramètres!$B$4+IFERROR(INDEX(Données!$I$2:$I$190,$H44),0) | J44: =Paramètres!$B$4+IFERROR(INDEX(Données!$I$2:$I$190,MIN($H44,160)),0) | K44: =I44-J44 | L44: =IF(43=1,E44,L43+E44) | M44: =G44-IFERROR(INDEX(Données!$K$2:$K$190,$H44),0)
A45: 44 | B45: =IF(44=1,0,H44) | C45: =Paramètres!$B$4+IFERROR(INDEX(Données!$I$2:$I$190,$B45),0) | D45: =C45*Paramètres!$B$3 | E45: =(Paramètres!$B$4*Paramètres!$B$6+IFERROR(INDEX(Données!$J$2:$J$190,$B45),0))*Paramètres!$B$3 | F45: =E45*Paramètres!$B$5 | G45: =IF(44=1,F45,G44+F45) | H45: =MIN(189,$B45+Paramètres!$B$7,COUNTIF(Données!$K$2:$K$190,"<="&G45)) | I45: =Paramètres!$B$4+IFERROR(INDEX(Données!$I$2:$I$190,$H45),0) | J45: =Paramètres!$B$4+IFERROR(INDEX(Données!$I$2:$I$190,MIN($H45,160)),0) | K45: =I45-J45 | L45: =IF(44=1,E45,L44+E45) | M45: =G45-IFERROR(INDEX(Données!$K$2:$K$190,$H45),0)
A46: 45 | B46: =IF(45=1,0,H45) | C46: =Paramètres!$B$4+IFERROR(INDEX(Données!$I$2:$I$190,$B46),0) | D46: =C46*Paramètres!$B$3 | E46: =(Paramètres!$B$4*Paramètres!$B$6+IFERROR(INDEX(Données!$J$2:$J$190,$B46),0))*Paramètres!$B$3 | F46: =E46*Paramètres!$B$5 | G46: =IF(45=1,F46,G45+F46) | H46: =MIN(189,$B46+Paramètres!$B$7,COUNTIF(Données!$K$2:$K$190,"<="&G46)) | I46: =Paramètres!$B$4+IFERROR(INDEX(Données!$I$2:$I$190,$H46),0) | J46: =Paramètres!$B$4+IFERROR(INDEX(Données!$I$2:$I$190,MIN($H46,160)),0) | K46: =I46-J46 | L46: =IF(45=1,E46,L45+E46) | M46: =G46-IFERROR(INDEX(Données!$K$2:$K$190,$H46),0)
A47: 46 | B47: =IF(46=1,0,H46) | C47: =Paramètres!$B$4+IFERROR(INDEX(Données!$I$2:$I$190,$B47),0) | D47: =C47*Paramètres!$B$3 | E47: =(Paramètres!$B$4*Paramètres!$B$6+IFERROR(INDEX(Données!$J$2:$J$190,$B47),0))*Paramètres!$B$3 | F47: =E47*Paramètres!$B$5 | G47: =IF(46=1,F47,G46+F47) | H47: =MIN(189,$B47+Paramètres!$B$7,COUNTIF(Données!$K$2:$K$190,"<="&G47)) | I47: =Paramètres!$B$4+IFERROR(INDEX(Données!$I$2:$I$190,$H47),0) | J47: =Paramètres!$B$4+IFERROR(INDEX(Données!$I$2:$I$190,MIN($H47,160)),0) | K47: =I47-J47 | L47: =IF(46=1,E47,L46+E47) | M47: =G47-IFERROR(INDEX(Données!$K$2:$K$190,$H47),0)
A48: 47 | B48: =IF(47=1,0,H47) | C48: =Paramètres!$B$4+IFERROR(INDEX(Données!$I$2:$I$190,$B48),0) | D48: =C48*Paramètres!$B$3 | E48: =(Paramètres!$B$4*Paramètres!$B$6+IFERROR(INDEX(Données!$J$2:$J$190,$B48),0))*Paramètres!$B$3 | F48: =E48*Paramètres!$B$5 | G48: =IF(47=1,F48,G47+F48) | H48: =MIN(189,$B48+Paramètres!$B$7,COUNTIF(Données!$K$2:$K$190,"<="&G48)) | I48: =Paramètres!$B$4+IFERROR(INDEX(Données!$I$2:$I$190,$H48),0) | J48: =Paramètres!$B$4+IFERROR(INDEX(Données!$I$2:$I$190,MIN($H48,160)),0) | K48: =I48-J48 | L48: =IF(47=1,E48,L47+E48) | M48: =G48-IFERROR(INDEX(Données!$K$2:$K$190,$H48),0)
A49: 48 | B49: =IF(48=1,0,H48) | C49: =Paramètres!$B$4+IFERROR(INDEX(Données!$I$2:$I$190,$B49),0) | D49: =C49*Paramètres!$B$3 | E49: =(Paramètres!$B$4*Paramètres!$B$6+IFERROR(INDEX(Données!$J$2:$J$190,$B49),0))*Paramètres!$B$3 | F49: =E49*Paramètres!$B$5 | G49: =IF(48=1,F49,G48+F49) | H49: =MIN(189,$B49+Paramètres!$B$7,COUNTIF(Données!$K$2:$K$190,"<="&G49)) | I49: =Paramètres!$B$4+IFERROR(INDEX(Données!$I$2:$I$190,$H49),0) | J49: =Paramètres!$B$4+IFERROR(INDEX(Données!$I$2:$I$190,MIN($H49,160)),0) | K49: =I49-J49 | L49: =IF(48=1,E49,L48+E49) | M49: =G49-IFERROR(INDEX(Données!$K$2:$K$190,$H49),0)
A50: 49 | B50: =IF(49=1,0,H49) | C50: =Paramètres!$B$4+IFERROR(INDEX(Données!$I$2:$I$190,$B50),0) | D50: =C50*Paramètres!$B$3 | E50: =(Paramètres!$B$4*Paramètres!$B$6+IFERROR(INDEX(Données!$J$2:$J$190,$B50),0))*Paramètres!$B$3 | F50: =E50*Paramètres!$B$5 | G50: =IF(49=1,F50,G49+F50) | H50: =MIN(189,$B50+Paramètres!$B$7,COUNTIF(Données!$K$2:$K$190,"<="&G50)) | I50: =Paramètres!$B$4+IFERROR(INDEX(Données!$I$2:$I$190,$H50),0) | J50: =Paramètres!$B$4+IFERROR(INDEX(Données!$I$2:$I$190,MIN($H50,160)),0) | K50: =I50-J50 | L50: =IF(49=1,E50,L49+E50) | M50: =G50-IFERROR(INDEX(Données!$K$2:$K$190,$H50),0)
A51: 50 | B51: =IF(50=1,0,H50) | C51: =Paramètres!$B$4+IFERROR(INDEX(Données!$I$2:$I$190,$B51),0) | D51: =C51*Paramètres!$B$3 | E51: =(Paramètres!$B$4*Paramètres!$B$6+IFERROR(INDEX(Données!$J$2:$J$190,$B51),0))*Paramètres!$B$3 | F51: =E51*Paramètres!$B$5 | G51: =IF(50=1,F51,G50+F51) | H51: =MIN(189,$B51+Paramètres!$B$7,COUNTIF(Données!$K$2:$K$190,"<="&G51)) | I51: =Paramètres!$B$4+IFERROR(INDEX(Données!$I$2:$I$190,$H51),0) | J51: =Paramètres!$B$4+IFERROR(INDEX(Données!$I$2:$I$190,MIN($H51,160)),0) | K51: =I51-J51 | L51: =IF(50=1,E51,L50+E51) | M51: =G51-IFERROR(INDEX(Données!$K$2:$K$190,$H51),0)
A52: 51 | B52: =IF(51=1,0,H51) | C52: =Paramètres!$B$4+IFERROR(INDEX(Données!$I$2:$I$190,$B52),0) | D52: =C52*Paramètres!$B$3 | E52: =(Paramètres!$B$4*Paramètres!$B$6+IFERROR(INDEX(Données!$J$2:$J$190,$B52),0))*Paramètres!$B$3 | F52: =E52*Paramètres!$B$5 | G52: =IF(51=1,F52,G51+F52) | H52: =MIN(189,$B52+Paramètres!$B$7,COUNTIF(Données!$K$2:$K$190,"<="&G52)) | I52: =Paramètres!$B$4+IFERROR(INDEX(Données!$I$2:$I$190,$H52),0) | J52: =Paramètres!$B$4+IFERROR(INDEX(Données!$I$2:$I$190,MIN($H52,160)),0) | K52: =I52-J52 | L52: =IF(51=1,E52,L51+E52) | M52: =G52-IFERROR(INDEX(Données!$K$2:$K$190,$H52),0)
A53: 52 | B53: =IF(52=1,0,H52) | C53: =Paramètres!$B$4+IFERROR(INDEX(Données!$I$2:$I$190,$B53),0) | D53: =C53*Paramètres!$B$3 | E53: =(Paramètres!$B$4*Paramètres!$B$6+IFERROR(INDEX(Données!$J$2:$J$190,$B53),0))*Paramètres!$B$3 | F53: =E53*Paramètres!$B$5 | G53: =IF(52=1,F53,G52+F53) | H53: =MIN(189,$B53+Paramètres!$B$7,COUNTIF(Données!$K$2:$K$190,"<="&G53)) | I53: =Paramètres!$B$4+IFERROR(INDEX(Données!$I$2:$I$190,$H53),0) | J53: =Paramètres!$B$4+IFERROR(INDEX(Données!$I$2:$I$190,MIN($H53,160)),0) | K53: =I53-J53 | L53: =IF(52=1,E53,L52+E53) | M53: =G53-IFERROR(INDEX(Données!$K$2:$K$190,$H53),0)
A54: 53 | B54: =IF(53=1,0,H53) | C54: =Paramètres!$B$4+IFERROR(INDEX(Données!$I$2:$I$190,$B54),0) | D54: =C54*Paramètres!$B$3 | E54: =(Paramètres!$B$4*Paramètres!$B$6+IFERROR(INDEX(Données!$J$2:$J$190,$B54),0))*Paramètres!$B$3 | F54: =E54*Paramètres!$B$5 | G54: =IF(53=1,F54,G53+F54) | H54: =MIN(189,$B54+Paramètres!$B$7,COUNTIF(Données!$K$2:$K$190,"<="&G54)) | I54: =Paramètres!$B$4+IFERROR(INDEX(Données!$I$2:$I$190,$H54),0) | J54: =Paramètres!$B$4+IFERROR(INDEX(Données!$I$2:$I$190,MIN($H54,160)),0) | K54: =I54-J54 | L54: =IF(53=1,E54,L53+E54) | M54: =G54-IFERROR(INDEX(Données!$K$2:$K$190,$H54),0)
A55: 54 | B55: =IF(54=1,0,H54) | C55: =Paramètres!$B$4+IFERROR(INDEX(Données!$I$2:$I$190,$B55),0) | D55: =C55*Paramètres!$B$3 | E55: =(Paramètres!$B$4*Paramètres!$B$6+IFERROR(INDEX(Données!$J$2:$J$190,$B55),0))*Paramètres!$B$3 | F55: =E55*Paramètres!$B$5 | G55: =IF(54=1,F55,G54+F55) | H55: =MIN(189,$B55+Paramètres!$B$7,COUNTIF(Données!$K$2:$K$190,"<="&G55)) | I55: =Paramètres!$B$4+IFERROR(INDEX(Données!$I$2:$I$190,$H55),0) | J55: =Paramètres!$B$4+IFERROR(INDEX(Données!$I$2:$I$190,MIN($H55,160)),0) | K55: =I55-J55 | L55: =IF(54=1,E55,L54+E55) | M55: =G55-IFERROR(INDEX(Données!$K$2:$K$190,$H55),0)
A56: 55 | B56: =IF(55=1,0,H55) | C56: =Paramètres!$B$4+IFERROR(INDEX(Données!$I$2:$I$190,$B56),0) | D56: =C56*Paramètres!$B$3 | E56: =(Paramètres!$B$4*Paramètres!$B$6+IFERROR(INDEX(Données!$J$2:$J$190,$B56),0))*Paramètres!$B$3 | F56: =E56*Paramètres!$B$5 | G56: =IF(55=1,F56,G55+F56) | H56: =MIN(189,$B56+Paramètres!$B$7,COUNTIF(Données!$K$2:$K$190,"<="&G56)) | I56: =Paramètres!$B$4+IFERROR(INDEX(Données!$I$2:$I$190,$H56),0) | J56: =Paramètres!$B$4+IFERROR(INDEX(Données!$I$2:$I$190,MIN($H56,160)),0) | K56: =I56-J56 | L56: =IF(55=1,E56,L55+E56) | M56: =G56-IFERROR(INDEX(Données!$K$2:$K$190,$H56),0)
A57: 56 | B57: =IF(56=1,0,H56) | C57: =Paramètres!$B$4+IFERROR(INDEX(Données!$I$2:$I$190,$B57),0) | D57: =C57*Paramètres!$B$3 | E57: =(Paramètres!$B$4*Paramètres!$B$6+IFERROR(INDEX(Données!$J$2:$J$190,$B57),0))*Paramètres!$B$3 | F57: =E57*Paramètres!$B$5 | G57: =IF(56=1,F57,G56+F57) | H57: =MIN(189,$B57+Paramètres!$B$7,COUNTIF(Données!$K$2:$K$190,"<="&G57)) | I57: =Paramètres!$B$4+IFERROR(INDEX(Données!$I$2:$I$190,$H57),0) | J57: =Paramètres!$B$4+IFERROR(INDEX(Données!$I$2:$I$190,MIN($H57,160)),0) | K57: =I57-J57 | L57: =IF(56=1,E57,L56+E57) | M57: =G57-IFERROR(INDEX(Données!$K$2:$K$190,$H57),0)
A58: 57 | B58: =IF(57=1,0,H57) | C58: =Paramètres!$B$4+IFERROR(INDEX(Données!$I$2:$I$190,$B58),0) | D58: =C58*Paramètres!$B$3 | E58: =(Paramètres!$B$4*Paramètres!$B$6+IFERROR(INDEX(Données!$J$2:$J$190,$B58),0))*Paramètres!$B$3 | F58: =E58*Paramètres!$B$5 | G58: =IF(57=1,F58,G57+F58) | H58: =MIN(189,$B58+Paramètres!$B$7,COUNTIF(Données!$K$2:$K$190,"<="&G58)) | I58: =Paramètres!$B$4+IFERROR(INDEX(Données!$I$2:$I$190,$H58),0) | J58: =Paramètres!$B$4+IFERROR(INDEX(Données!$I$2:$I$190,MIN($H58,160)),0) | K58: =I58-J58 | L58: =IF(57=1,E58,L57+E58) | M58: =G58-IFERROR(INDEX(Données!$K$2:$K$190,$H58),0)
A59: 58 | B59: =IF(58=1,0,H58) | C59: =Paramètres!$B$4+IFERROR(INDEX(Données!$I$2:$I$190,$B59),0) | D59: =C59*Paramètres!$B$3 | E59: =(Paramètres!$B$4*Paramètres!$B$6+IFERROR(INDEX(Données!$J$2:$J$190,$B59),0))*Paramètres!$B$3 | F59: =E59*Paramètres!$B$5 | G59: =IF(58=1,F59,G58+F59) | H59: =MIN(189,$B59+Paramètres!$B$7,COUNTIF(Données!$K$2:$K$190,"<="&G59)) | I59: =Paramètres!$B$4+IFERROR(INDEX(Données!$I$2:$I$190,$H59),0) | J59: =Paramètres!$B$4+IFERROR(INDEX(Données!$I$2:$I$190,MIN($H59,160)),0) | K59: =I59-J59 | L59: =IF(58=1,E59,L58+E59) | M59: =G59-IFERROR(INDEX(Données!$K$2:$K$190,$H59),0)
A60: 59 | B60: =IF(59=1,0,H59) | C60: =Paramètres!$B$4+IFERROR(INDEX(Données!$I$2:$I$190,$B60),0) | D60: =C60*Paramètres!$B$3 | E60: =(Paramètres!$B$4*Paramètres!$B$6+IFERROR(INDEX(Données!$J$2:$J$190,$B60),0))*Paramètres!$B$3 | F60: =E60*Paramètres!$B$5 | G60: =IF(59=1,F60,G59+F60) | H60: =MIN(189,$B60+Paramètres!$B$7,COUNTIF(Données!$K$2:$K$190,"<="&G60)) | I60: =Paramètres!$B$4+IFERROR(INDEX(Données!$I$2:$I$190,$H60),0) | J60: =Paramètres!$B$4+IFERROR(INDEX(Données!$I$2:$I$190,MIN($H60,160)),0) | K60: =I60-J60 | L60: =IF(59=1,E60,L59+E60) | M60: =G60-IFERROR(INDEX(Données!$K$2:$K$190,$H60),0)
A61: 60 | B61: =IF(60=1,0,H60) | C61: =Paramètres!$B$4+IFERROR(INDEX(Données!$I$2:$I$190,$B61),0) | D61: =C61*Paramètres!$B$3 | E61: =(Paramètres!$B$4*Paramètres!$B$6+IFERROR(INDEX(Données!$J$2:$J$190,$B61),0))*Paramètres!$B$3 | F61: =E61*Paramètres!$B$5 | G61: =IF(60=1,F61,G60+F61) | H61: =MIN(189,$B61+Paramètres!$B$7,COUNTIF(Données!$K$2:$K$190,"<="&G61)) | I61: =Paramètres!$B$4+IFERROR(INDEX(Données!$I$2:$I$190,$H61),0) | J61: =Paramètres!$B$4+IFERROR(INDEX(Données!$I$2:$I$190,MIN($H61,160)),0) | K61: =I61-J61 | L61: =IF(60=1,E61,L60+E61) | M61: =G61-IFERROR(INDEX(Données!$K$2:$K$190,$H61),0)
A62: 61 | B62: =IF(61=1,0,H61) | C62: =Paramètres!$B$4+IFERROR(INDEX(Données!$I$2:$I$190,$B62),0) | D62: =C62*Paramètres!$B$3 | E62: =(Paramètres!$B$4*Paramètres!$B$6+IFERROR(INDEX(Données!$J$2:$J$190,$B62),0))*Paramètres!$B$3 | F62: =E62*Paramètres!$B$5 | G62: =IF(61=1,F62,G61+F62) | H62: =MIN(189,$B62+Paramètres!$B$7,COUNTIF(Données!$K$2:$K$190,"<="&G62)) | I62: =Paramètres!$B$4+IFERROR(INDEX(Données!$I$2:$I$190,$H62),0) | J62: =Paramètres!$B$4+IFERROR(INDEX(Données!$I$2:$I$190,MIN($H62,160)),0) | K62: =I62-J62 | L62: =IF(61=1,E62,L61+E62) | M62: =G62-IFERROR(INDEX(Données!$K$2:$K$190,$H62),0)
A63: 62 | B63: =IF(62=1,0,H62) | C63: =Paramètres!$B$4+IFERROR(INDEX(Données!$I$2:$I$190,$B63),0) | D63: =C63*Paramètres!$B$3 | E63: =(Paramètres!$B$4*Paramètres!$B$6+IFERROR(INDEX(Données!$J$2:$J$190,$B63),0))*Paramètres!$B$3 | F63: =E63*Paramètres!$B$5 | G63: =IF(62=1,F63,G62+F63) | H63: =MIN(189,$B63+Paramètres!$B$7,COUNTIF(Données!$K$2:$K$190,"<="&G63)) | I63: =Paramètres!$B$4+IFERROR(INDEX(Données!$I$2:$I$190,$H63),0) | J63: =Paramètres!$B$4+IFERROR(INDEX(Données!$I$2:$I$190,MIN($H63,160)),0) | K63: =I63-J63 | L63: =IF(62=1,E63,L62+E63) | M63: =G63-IFERROR(INDEX(Données!$K$2:$K$190,$H63),0)
A64: 63 | B64: =IF(63=1,0,H63) | C64: =Paramètres!$B$4+IFERROR(INDEX(Données!$I$2:$I$190,$B64),0) | D64: =C64*Paramètres!$B$3 | E64: =(Paramètres!$B$4*Paramètres!$B$6+IFERROR(INDEX(Données!$J$2:$J$190,$B64),0))*Paramètres!$B$3 | F64: =E64*Paramètres!$B$5 | G64: =IF(63=1,F64,G63+F64) | H64: =MIN(189,$B64+Paramètres!$B$7,COUNTIF(Données!$K$2:$K$190,"<="&G64)) | I64: =Paramètres!$B$4+IFERROR(INDEX(Données!$I$2:$I$190,$H64),0) | J64: =Paramètres!$B$4+IFERROR(INDEX(Données!$I$2:$I$190,MIN($H64,160)),0) | K64: =I64-J64 | L64: =IF(63=1,E64,L63+E64) | M64: =G64-IFERROR(INDEX(Données!$K$2:$K$190,$H64),0)
A65: 64 | B65: =IF(64=1,0,H64) | C65: =Paramètres!$B$4+IFERROR(INDEX(Données!$I$2:$I$190,$B65),0) | D65: =C65*Paramètres!$B$3 | E65: =(Paramètres!$B$4*Paramètres!$B$6+IFERROR(INDEX(Données!$J$2:$J$190,$B65),0))*Paramètres!$B$3 | F65: =E65*Paramètres!$B$5 | G65: =IF(64=1,F65,G64+F65) | H65: =MIN(189,$B65+Paramètres!$B$7,COUNTIF(Données!$K$2:$K$190,"<="&G65)) | I65: =Paramètres!$B$4+IFERROR(INDEX(Données!$I$2:$I$190,$H65),0) | J65: =Paramètres!$B$4+IFERROR(INDEX(Données!$I$2:$I$190,MIN($H65,160)),0) | K65: =I65-J65 | L65: =IF(64=1,E65,L64+E65) | M65: =G65-IFERROR(INDEX(Données!$K$2:$K$190,$H65),0)
A66: 65 | B66: =IF(65=1,0,H65) | C66: =Paramètres!$B$4+IFERROR(INDEX(Données!$I$2:$I$190,$B66),0) | D66: =C66*Paramètres!$B$3 | E66: =(Paramètres!$B$4*Paramètres!$B$6+IFERROR(INDEX(Données!$J$2:$J$190,$B66),0))*Paramètres!$B$3 | F66: =E66*Paramètres!$B$5 | G66: =IF(65=1,F66,G65+F66) | H66: =MIN(189,$B66+Paramètres!$B$7,COUNTIF(Données!$K$2:$K$190,"<="&G66)) | I66: =Paramètres!$B$4+IFERROR(INDEX(Données!$I$2:$I$190,$H66),0) | J66: =Paramètres!$B$4+IFERROR(INDEX(Données!$I$2:$I$190,MIN($H66,160)),0) | K66: =I66-J66 | L66: =IF(65=1,E66,L65+E66) | M66: =G66-IFERROR(INDEX(Données!$K$2:$K$190,$H66),0)
A67: 66 | B67: =IF(66=1,0,H66) | C67: =Paramètres!$B$4+IFERROR(INDEX(Données!$I$2:$I$190,$B67),0) | D67: =C67*Paramètres!$B$3 | E67: =(Paramètres!$B$4*Paramètres!$B$6+IFERROR(INDEX(Données!$J$2:$J$190,$B67),0))*Paramètres!$B$3 | F67: =E67*Paramètres!$B$5 | G67: =IF(66=1,F67,G66+F67) | H67: =MIN(189,$B67+Paramètres!$B$7,COUNTIF(Données!$K$2:$K$190,"<="&G67)) | I67: =Paramètres!$B$4+IFERROR(INDEX(Données!$I$2:$I$190,$H67),0) | J67: =Paramètres!$B$4+IFERROR(INDEX(Données!$I$2:$I$190,MIN($H67,160)),0) | K67: =I67-J67 | L67: =IF(66=1,E67,L66+E67) | M67: =G67-IFERROR(INDEX(Données!$K$2:$K$190,$H67),0)
A68: 67 | B68: =IF(67=1,0,H67) | C68: =Paramètres!$B$4+IFERROR(INDEX(Données!$I$2:$I$190,$B68),0) | D68: =C68*Paramètres!$B$3 | E68: =(Paramètres!$B$4*Paramètres!$B$6+IFERROR(INDEX(Données!$J$2:$J$190,$B68),0))*Paramètres!$B$3 | F68: =E68*Paramètres!$B$5 | G68: =IF(67=1,F68,G67+F68) | H68: =MIN(189,$B68+Paramètres!$B$7,COUNTIF(Données!$K$2:$K$190,"<="&G68)) | I68: =Paramètres!$B$4+IFERROR(INDEX(Données!$I$2:$I$190,$H68),0) | J68: =Paramètres!$B$4+IFERROR(INDEX(Données!$I$2:$I$190,MIN($H68,160)),0) | K68: =I68-J68 | L68: =IF(67=1,E68,L67+E68) | M68: =G68-IFERROR(INDEX(Données!$K$2:$K$190,$H68),0)
A69: 68 | B69: =IF(68=1,0,H68) | C69: =Paramètres!$B$4+IFERROR(INDEX(Données!$I$2:$I$190,$B69),0) | D69: =C69*Paramètres!$B$3 | E69: =(Paramètres!$B$4*Paramètres!$B$6+IFERROR(INDEX(Données!$J$2:$J$190,$B69),0))*Paramètres!$B$3 | F69: =E69*Paramètres!$B$5 | G69: =IF(68=1,F69,G68+F69) | H69: =MIN(189,$B69+Paramètres!$B$7,COUNTIF(Données!$K$2:$K$190,"<="&G69)) | I69: =Paramètres!$B$4+IFERROR(INDEX(Données!$I$2:$I$190,$H69),0) | J69: =Paramètres!$B$4+IFERROR(INDEX(Données!$I$2:$I$190,MIN($H69,160)),0) | K69: =I69-J69 | L69: =IF(68=1,E69,L68+E69) | M69: =G69-IFERROR(INDEX(Données!$K$2:$K$190,$H69),0)
A70: 69 | B70: =IF(69=1,0,H69) | C70: =Paramètres!$B$4+IFERROR(INDEX(Données!$I$2:$I$190,$B70),0) | D70: =C70*Paramètres!$B$3 | E70: =(Paramètres!$B$4*Paramètres!$B$6+IFERROR(INDEX(Données!$J$2:$J$190,$B70),0))*Paramètres!$B$3 | F70: =E70*Paramètres!$B$5 | G70: =IF(69=1,F70,G69+F70) | H70: =MIN(189,$B70+Paramètres!$B$7,COUNTIF(Données!$K$2:$K$190,"<="&G70)) | I70: =Paramètres!$B$4+IFERROR(INDEX(Données!$I$2:$I$190,$H70),0) | J70: =Paramètres!$B$4+IFERROR(INDEX(Données!$I$2:$I$190,MIN($H70,160)),0) | K70: =I70-J70 | L70: =IF(69=1,E70,L69+E70) | M70: =G70-IFERROR(INDEX(Données!$K$2:$K$190,$H70),0)
A71: 70 | B71: =IF(70=1,0,H70) | C71: =Paramètres!$B$4+IFERROR(INDEX(Données!$I$2:$I$190,$B71),0) | D71: =C71*Paramètres!$B$3 | E71: =(Paramètres!$B$4*Paramètres!$B$6+IFERROR(INDEX(Données!$J$2:$J$190,$B71),0))*Paramètres!$B$3 | F71: =E71*Paramètres!$B$5 | G71: =IF(70=1,F71,G70+F71) | H71: =MIN(189,$B71+Paramètres!$B$7,COUNTIF(Données!$K$2:$K$190,"<="&G71)) | I71: =Paramètres!$B$4+IFERROR(INDEX(Données!$I$2:$I$190,$H71),0) | J71: =Paramètres!$B$4+IFERROR(INDEX(Données!$I$2:$I$190,MIN($H71,160)),0) | K71: =I71-J71 | L71: =IF(70=1,E71,L70+E71) | M71: =G71-IFERROR(INDEX(Données!$K$2:$K$190,$H71),0)
A72: 71 | B72: =IF(71=1,0,H71) | C72: =Paramètres!$B$4+IFERROR(INDEX(Données!$I$2:$I$190,$B72),0) | D72: =C72*Paramètres!$B$3 | E72: =(Paramètres!$B$4*Paramètres!$B$6+IFERROR(INDEX(Données!$J$2:$J$190,$B72),0))*Paramètres!$B$3 | F72: =E72*Paramètres!$B$5 | G72: =IF(71=1,F72,G71+F72) | H72: =MIN(189,$B72+Paramètres!$B$7,COUNTIF(Données!$K$2:$K$190,"<="&G72)) | I72: =Paramètres!$B$4+IFERROR(INDEX(Données!$I$2:$I$190,$H72),0) | J72: =Paramètres!$B$4+IFERROR(INDEX(Données!$I$2:$I$190,MIN($H72,160)),0) | K72: =I72-J72 | L72: =IF(71=1,E72,L71+E72) | M72: =G72-IFERROR(INDEX(Données!$K$2:$K$190,$H72),0)
A73: 72 | B73: =IF(72=1,0,H72) | C73: =Paramètres!$B$4+IFERROR(INDEX(Données!$I$2:$I$190,$B73),0) | D73: =C73*Paramètres!$B$3 | E73: =(Paramètres!$B$4*Paramètres!$B$6+IFERROR(INDEX(Données!$J$2:$J$190,$B73),0))*Paramètres!$B$3 | F73: =E73*Paramètres!$B$5 | G73: =IF(72=1,F73,G72+F73) | H73: =MIN(189,$B73+Paramètres!$B$7,COUNTIF(Données!$K$2:$K$190,"<="&G73)) | I73: =Paramètres!$B$4+IFERROR(INDEX(Données!$I$2:$I$190,$H73),0) | J73: =Paramètres!$B$4+IFERROR(INDEX(Données!$I$2:$I$190,MIN($H73,160)),0) | K73: =I73-J73 | L73: =IF(72=1,E73,L72+E73) | M73: =G73-IFERROR(INDEX(Données!$K$2:$K$190,$H73),0)
A74: 73 | B74: =IF(73=1,0,H73) | C74: =Paramètres!$B$4+IFERROR(INDEX(Données!$I$2:$I$190,$B74),0) | D74: =C74*Paramètres!$B$3 | E74: =(Paramètres!$B$4*Paramètres!$B$6+IFERROR(INDEX(Données!$J$2:$J$190,$B74),0))*Paramètres!$B$3 | F74: =E74*Paramètres!$B$5 | G74: =IF(73=1,F74,G73+F74) | H74: =MIN(189,$B74+Paramètres!$B$7,COUNTIF(Données!$K$2:$K$190,"<="&G74)) | I74: =Paramètres!$B$4+IFERROR(INDEX(Données!$I$2:$I$190,$H74),0) | J74: =Paramètres!$B$4+IFERROR(INDEX(Données!$I$2:$I$190,MIN($H74,160)),0) | K74: =I74-J74 | L74: =IF(73=1,E74,L73+E74) | M74: =G74-IFERROR(INDEX(Données!$K$2:$K$190,$H74),0)
A75: 74 | B75: =IF(74=1,0,H74) | C75: =Paramètres!$B$4+IFERROR(INDEX(Données!$I$2:$I$190,$B75),0) | D75: =C75*Paramètres!$B$3 | E75: =(Paramètres!$B$4*Paramètres!$B$6+IFERROR(INDEX(Données!$J$2:$J$190,$B75),0))*Paramètres!$B$3 | F75: =E75*Paramètres!$B$5 | G75: =IF(74=1,F75,G74+F75) | H75: =MIN(189,$B75+Paramètres!$B$7,COUNTIF(Données!$K$2:$K$190,"<="&G75)) | I75: =Paramètres!$B$4+IFERROR(INDEX(Données!$I$2:$I$190,$H75),0) | J75: =Paramètres!$B$4+IFERROR(INDEX(Données!$I$2:$I$190,MIN($H75,160)),0) | K75: =I75-J75 | L75: =IF(74=1,E75,L74+E75) | M75: =G75-IFERROR(INDEX(Données!$K$2:$K$190,$H75),0)
A76: 75 | B76: =IF(75=1,0,H75) | C76: =Paramètres!$B$4+IFERROR(INDEX(Données!$I$2:$I$190,$B76),0) | D76: =C76*Paramètres!$B$3 | E76: =(Paramètres!$B$4*Paramètres!$B$6+IFERROR(INDEX(Données!$J$2:$J$190,$B76),0))*Paramètres!$B$3 | F76: =E76*Paramètres!$B$5 | G76: =IF(75=1,F76,G75+F76) | H76: =MIN(189,$B76+Paramètres!$B$7,COUNTIF(Données!$K$2:$K$190,"<="&G76)) | I76: =Paramètres!$B$4+IFERROR(INDEX(Données!$I$2:$I$190,$H76),0) | J76: =Paramètres!$B$4+IFERROR(INDEX(Données!$I$2:$I$190,MIN($H76,160)),0) | K76: =I76-J76 | L76: =IF(75=1,E76,L75+E76) | M76: =G76-IFERROR(INDEX(Données!$K$2:$K$190,$H76),0)
A77: 76 | B77: =IF(76=1,0,H76) | C77: =Paramètres!$B$4+IFERROR(INDEX(Données!$I$2:$I$190,$B77),0) | D77: =C77*Paramètres!$B$3 | E77: =(Paramètres!$B$4*Paramètres!$B$6+IFERROR(INDEX(Données!$J$2:$J$190,$B77),0))*Paramètres!$B$3 | F77: =E77*Paramètres!$B$5 | G77: =IF(76=1,F77,G76+F77) | H77: =MIN(189,$B77+Paramètres!$B$7,COUNTIF(Données!$K$2:$K$190,"<="&G77)) | I77: =Paramètres!$B$4+IFERROR(INDEX(Données!$I$2:$I$190,$H77),0) | J77: =Paramètres!$B$4+IFERROR(INDEX(Données!$I$2:$I$190,MIN($H77,160)),0) | K77: =I77-J77 | L77: =IF(76=1,E77,L76+E77) | M77: =G77-IFERROR(INDEX(Données!$K$2:$K$190,$H77),0)
A78: 77 | B78: =IF(77=1,0,H77) | C78: =Paramètres!$B$4+IFERROR(INDEX(Données!$I$2:$I$190,$B78),0) | D78: =C78*Paramètres!$B$3 | E78: =(Paramètres!$B$4*Paramètres!$B$6+IFERROR(INDEX(Données!$J$2:$J$190,$B78),0))*Paramètres!$B$3 | F78: =E78*Paramètres!$B$5 | G78: =IF(77=1,F78,G77+F78) | H78: =MIN(189,$B78+Paramètres!$B$7,COUNTIF(Données!$K$2:$K$190,"<="&G78)) | I78: =Paramètres!$B$4+IFERROR(INDEX(Données!$I$2:$I$190,$H78),0) | J78: =Paramètres!$B$4+IFERROR(INDEX(Données!$I$2:$I$190,MIN($H78,160)),0) | K78: =I78-J78 | L78: =IF(77=1,E78,L77+E78) | M78: =G78-IFERROR(INDEX(Données!$K$2:$K$190,$H78),0)
A79: 78 | B79: =IF(78=1,0,H78) | C79: =Paramètres!$B$4+IFERROR(INDEX(Données!$I$2:$I$190,$B79),0) | D79: =C79*Paramètres!$B$3 | E79: =(Paramètres!$B$4*Paramètres!$B$6+IFERROR(INDEX(Données!$J$2:$J$190,$B79),0))*Paramètres!$B$3 | F79: =E79*Paramètres!$B$5 | G79: =IF(78=1,F79,G78+F79) | H79: =MIN(189,$B79+Paramètres!$B$7,COUNTIF(Données!$K$2:$K$190,"<="&G79)) | I79: =Paramètres!$B$4+IFERROR(INDEX(Données!$I$2:$I$190,$H79),0) | J79: =Paramètres!$B$4+IFERROR(INDEX(Données!$I$2:$I$190,MIN($H79,160)),0) | K79: =I79-J79 | L79: =IF(78=1,E79,L78+E79) | M79: =G79-IFERROR(INDEX(Données!$K$2:$K$190,$H79),0)
A80: 79 | B80: =IF(79=1,0,H79) | C80: =Paramètres!$B$4+IFERROR(INDEX(Données!$I$2:$I$190,$B80),0) | D80: =C80*Paramètres!$B$3 | E80: =(Paramètres!$B$4*Paramètres!$B$6+IFERROR(INDEX(Données!$J$2:$J$190,$B80),0))*Paramètres!$B$3 | F80: =E80*Paramètres!$B$5 | G80: =IF(79=1,F80,G79+F80) | H80: =MIN(189,$B80+Paramètres!$B$7,COUNTIF(Données!$K$2:$K$190,"<="&G80)) | I80: =Paramètres!$B$4+IFERROR(INDEX(Données!$I$2:$I$190,$H80),0) | J80: =Paramètres!$B$4+IFERROR(INDEX(Données!$I$2:$I$190,MIN($H80,160)),0) | K80: =I80-J80 | L80: =IF(79=1,E80,L79+E80) | M80: =G80-IFERROR(INDEX(Données!$K$2:$K$190,$H80),0)
A81: 80 | B81: =IF(80=1,0,H80) | C81: =Paramètres!$B$4+IFERROR(INDEX(Données!$I$2:$I$190,$B81),0) | D81: =C81*Paramètres!$B$3 | E81: =(Paramètres!$B$4*Paramètres!$B$6+IFERROR(INDEX(Données!$J$2:$J$190,$B81),0))*Paramètres!$B$3 | F81: =E81*Paramètres!$B$5 | G81: =IF(80=1,F81,G80+F81) | H81: =MIN(189,$B81+Paramètres!$B$7,COUNTIF(Données!$K$2:$K$190,"<="&G81)) | I81: =Paramètres!$B$4+IFERROR(INDEX(Données!$I$2:$I$190,$H81),0) | J81: =Paramètres!$B$4+IFERROR(INDEX(Données!$I$2:$I$190,MIN($H81,160)),0) | K81: =I81-J81 | L81: =IF(80=1,E81,L80+E81) | M81: =G81-IFERROR(INDEX(Données!$K$2:$K$190,$H81),0)
A82: 81 | B82: =IF(81=1,0,H81) | C82: =Paramètres!$B$4+IFERROR(INDEX(Données!$I$2:$I$190,$B82),0) | D82: =C82*Paramètres!$B$3 | E82: =(Paramètres!$B$4*Paramètres!$B$6+IFERROR(INDEX(Données!$J$2:$J$190,$B82),0))*Paramètres!$B$3 | F82: =E82*Paramètres!$B$5 | G82: =IF(81=1,F82,G81+F82) | H82: =MIN(189,$B82+Paramètres!$B$7,COUNTIF(Données!$K$2:$K$190,"<="&G82)) | I82: =Paramètres!$B$4+IFERROR(INDEX(Données!$I$2:$I$190,$H82),0) | J82: =Paramètres!$B$4+IFERROR(INDEX(Données!$I$2:$I$190,MIN($H82,160)),0) | K82: =I82-J82 | L82: =IF(81=1,E82,L81+E82) | M82: =G82-IFERROR(INDEX(Données!$K$2:$K$190,$H82),0)
A83: 82 | B83: =IF(82=1,0,H82) | C83: =Paramètres!$B$4+IFERROR(INDEX(Données!$I$2:$I$190,$B83),0) | D83: =C83*Paramètres!$B$3 | E83: =(Paramètres!$B$4*Paramètres!$B$6+IFERROR(INDEX(Données!$J$2:$J$190,$B83),0))*Paramètres!$B$3 | F83: =E83*Paramètres!$B$5 | G83: =IF(82=1,F83,G82+F83) | H83: =MIN(189,$B83+Paramètres!$B$7,COUNTIF(Données!$K$2:$K$190,"<="&G83)) | I83: =Paramètres!$B$4+IFERROR(INDEX(Données!$I$2:$I$190,$H83),0) | J83: =Paramètres!$B$4+IFERROR(INDEX(Données!$I$2:$I$190,MIN($H83,160)),0) | K83: =I83-J83 | L83: =IF(82=1,E83,L82+E83) | M83: =G83-IFERROR(INDEX(Données!$K$2:$K$190,$H83),0)
A84: 83 | B84: =IF(83=1,0,H83) | C84: =Paramètres!$B$4+IFERROR(INDEX(Données!$I$2:$I$190,$B84),0) | D84: =C84*Paramètres!$B$3 | E84: =(Paramètres!$B$4*Paramètres!$B$6+IFERROR(INDEX(Données!$J$2:$J$190,$B84),0))*Paramètres!$B$3 | F84: =E84*Paramètres!$B$5 | G84: =IF(83=1,F84,G83+F84) | H84: =MIN(189,$B84+Paramètres!$B$7,COUNTIF(Données!$K$2:$K$190,"<="&G84)) | I84: =Paramètres!$B$4+IFERROR(INDEX(Données!$I$2:$I$190,$H84),0) | J84: =Paramètres!$B$4+IFERROR(INDEX(Données!$I$2:$I$190,MIN($H84,160)),0) | K84: =I84-J84 | L84: =IF(83=1,E84,L83+E84) | M84: =G84-IFERROR(INDEX(Données!$K$2:$K$190,$H84),0)
A85: 84 | B85: =IF(84=1,0,H84) | C85: =Paramètres!$B$4+IFERROR(INDEX(Données!$I$2:$I$190,$B85),0) | D85: =C85*Paramètres!$B$3 | E85: =(Paramètres!$B$4*Paramètres!$B$6+IFERROR(INDEX(Données!$J$2:$J$190,$B85),0))*Paramètres!$B$3 | F85: =E85*Paramètres!$B$5 | G85: =IF(84=1,F85,G84+F85) | H85: =MIN(189,$B85+Paramètres!$B$7,COUNTIF(Données!$K$2:$K$190,"<="&G85)) | I85: =Paramètres!$B$4+IFERROR(INDEX(Données!$I$2:$I$190,$H85),0) | J85: =Paramètres!$B$4+IFERROR(INDEX(Données!$I$2:$I$190,MIN($H85,160)),0) | K85: =I85-J85 | L85: =IF(84=1,E85,L84+E85) | M85: =G85-IFERROR(INDEX(Données!$K$2:$K$190,$H85),0)
A86: 85 | B86: =IF(85=1,0,H85) | C86: =Paramètres!$B$4+IFERROR(INDEX(Données!$I$2:$I$190,$B86),0) | D86: =C86*Paramètres!$B$3 | E86: =(Paramètres!$B$4*Paramètres!$B$6+IFERROR(INDEX(Données!$J$2:$J$190,$B86),0))*Paramètres!$B$3 | F86: =E86*Paramètres!$B$5 | G86: =IF(85=1,F86,G85+F86) | H86: =MIN(189,$B86+Paramètres!$B$7,COUNTIF(Données!$K$2:$K$190,"<="&G86)) | I86: =Paramètres!$B$4+IFERROR(INDEX(Données!$I$2:$I$190,$H86),0) | J86: =Paramètres!$B$4+IFERROR(INDEX(Données!$I$2:$I$190,MIN($H86,160)),0) | K86: =I86-J86 | L86: =IF(85=1,E86,L85+E86) | M86: =G86-IFERROR(INDEX(Données!$K$2:$K$190,$H86),0)
A87: 86 | B87: =IF(86=1,0,H86) | C87: =Paramètres!$B$4+IFERROR(INDEX(Données!$I$2:$I$190,$B87),0) | D87: =C87*Paramètres!$B$3 | E87: =(Paramètres!$B$4*Paramètres!$B$6+IFERROR(INDEX(Données!$J$2:$J$190,$B87),0))*Paramètres!$B$3 | F87: =E87*Paramètres!$B$5 | G87: =IF(86=1,F87,G86+F87) | H87: =MIN(189,$B87+Paramètres!$B$7,COUNTIF(Données!$K$2:$K$190,"<="&G87)) | I87: =Paramètres!$B$4+IFERROR(INDEX(Données!$I$2:$I$190,$H87),0) | J87: =Paramètres!$B$4+IFERROR(INDEX(Données!$I$2:$I$190,MIN($H87,160)),0) | K87: =I87-J87 | L87: =IF(86=1,E87,L86+E87) | M87: =G87-IFERROR(INDEX(Données!$K$2:$K$190,$H87),0)
A88: 87 | B88: =IF(87=1,0,H87) | C88: =Paramètres!$B$4+IFERROR(INDEX(Données!$I$2:$I$190,$B88),0) | D88: =C88*Paramètres!$B$3 | E88: =(Paramètres!$B$4*Paramètres!$B$6+IFERROR(INDEX(Données!$J$2:$J$190,$B88),0))*Paramètres!$B$3 | F88: =E88*Paramètres!$B$5 | G88: =IF(87=1,F88,G87+F88) | H88: =MIN(189,$B88+Paramètres!$B$7,COUNTIF(Données!$K$2:$K$190,"<="&G88)) | I88: =Paramètres!$B$4+IFERROR(INDEX(Données!$I$2:$I$190,$H88),0) | J88: =Paramètres!$B$4+IFERROR(INDEX(Données!$I$2:$I$190,MIN($H88,160)),0) | K88: =I88-J88 | L88: =IF(87=1,E88,L87+E88) | M88: =G88-IFERROR(INDEX(Données!$K$2:$K$190,$H88),0)
A89: 88 | B89: =IF(88=1,0,H88) | C89: =Paramètres!$B$4+IFERROR(INDEX(Données!$I$2:$I$190,$B89),0) | D89: =C89*Paramètres!$B$3 | E89: =(Paramètres!$B$4*Paramètres!$B$6+IFERROR(INDEX(Données!$J$2:$J$190,$B89),0))*Paramètres!$B$3 | F89: =E89*Paramètres!$B$5 | G89: =IF(88=1,F89,G88+F89) | H89: =MIN(189,$B89+Paramètres!$B$7,COUNTIF(Données!$K$2:$K$190,"<="&G89)) | I89: =Paramètres!$B$4+IFERROR(INDEX(Données!$I$2:$I$190,$H89),0) | J89: =Paramètres!$B$4+IFERROR(INDEX(Données!$I$2:$I$190,MIN($H89,160)),0) | K89: =I89-J89 | L89: =IF(88=1,E89,L88+E89) | M89: =G89-IFERROR(INDEX(Données!$K$2:$K$190,$H89),0)
A90: 89 | B90: =IF(89=1,0,H89) | C90: =Paramètres!$B$4+IFERROR(INDEX(Données!$I$2:$I$190,$B90),0) | D90: =C90*Paramètres!$B$3 | E90: =(Paramètres!$B$4*Paramètres!$B$6+IFERROR(INDEX(Données!$J$2:$J$190,$B90),0))*Paramètres!$B$3 | F90: =E90*Paramètres!$B$5 | G90: =IF(89=1,F90,G89+F90) | H90: =MIN(189,$B90+Paramètres!$B$7,COUNTIF(Données!$K$2:$K$190,"<="&G90)) | I90: =Paramètres!$B$4+IFERROR(INDEX(Données!$I$2:$I$190,$H90),0) | J90: =Paramètres!$B$4+IFERROR(INDEX(Données!$I$2:$I$190,MIN($H90,160)),0) | K90: =I90-J90 | L90: =IF(89=1,E90,L89+E90) | M90: =G90-IFERROR(INDEX(Données!$K$2:$K$190,$H90),0)
A91: 90 | B91: =IF(90=1,0,H90) | C91: =Paramètres!$B$4+IFERROR(INDEX(Données!$I$2:$I$190,$B91),0) | D91: =C91*Paramètres!$B$3 | E91: =(Paramètres!$B$4*Paramètres!$B$6+IFERROR(INDEX(Données!$J$2:$J$190,$B91),0))*Paramètres!$B$3 | F91: =E91*Paramètres!$B$5 | G91: =IF(90=1,F91,G90+F91) | H91: =MIN(189,$B91+Paramètres!$B$7,COUNTIF(Données!$K$2:$K$190,"<="&G91)) | I91: =Paramètres!$B$4+IFERROR(INDEX(Données!$I$2:$I$190,$H91),0) | J91: =Paramètres!$B$4+IFERROR(INDEX(Données!$I$2:$I$190,MIN($H91,160)),0) | K91: =I91-J91 | L91: =IF(90=1,E91,L90+E91) | M91: =G91-IFERROR(INDEX(Données!$K$2:$K$190,$H91),0)
A92: 91 | B92: =IF(91=1,0,H91) | C92: =Paramètres!$B$4+IFERROR(INDEX(Données!$I$2:$I$190,$B92),0) | D92: =C92*Paramètres!$B$3 | E92: =(Paramètres!$B$4*Paramètres!$B$6+IFERROR(INDEX(Données!$J$2:$J$190,$B92),0))*Paramètres!$B$3 | F92: =E92*Paramètres!$B$5 | G92: =IF(91=1,F92,G91+F92) | H92: =MIN(189,$B92+Paramètres!$B$7,COUNTIF(Données!$K$2:$K$190,"<="&G92)) | I92: =Paramètres!$B$4+IFERROR(INDEX(Données!$I$2:$I$190,$H92),0) | J92: =Paramètres!$B$4+IFERROR(INDEX(Données!$I$2:$I$190,MIN($H92,160)),0) | K92: =I92-J92 | L92: =IF(91=1,E92,L91+E92) | M92: =G92-IFERROR(INDEX(Données!$K$2:$K$190,$H92),0)
A93: 92 | B93: =IF(92=1,0,H92) | C93: =Paramètres!$B$4+IFERROR(INDEX(Données!$I$2:$I$190,$B93),0) | D93: =C93*Paramètres!$B$3 | E93: =(Paramètres!$B$4*Paramètres!$B$6+IFERROR(INDEX(Données!$J$2:$J$190,$B93),0))*Paramètres!$B$3 | F93: =E93*Paramètres!$B$5 | G93: =IF(92=1,F93,G92+F93) | H93: =MIN(189,$B93+Paramètres!$B$7,COUNTIF(Données!$K$2:$K$190,"<="&G93)) | I93: =Paramètres!$B$4+IFERROR(INDEX(Données!$I$2:$I$190,$H93),0) | J93: =Paramètres!$B$4+IFERROR(INDEX(Données!$I$2:$I$190,MIN($H93,160)),0) | K93: =I93-J93 | L93: =IF(92=1,E93,L92+E93) | M93: =G93-IFERROR(INDEX(Données!$K$2:$K$190,$H93),0)
A94: 93 | B94: =IF(93=1,0,H93) | C94: =Paramètres!$B$4+IFERROR(INDEX(Données!$I$2:$I$190,$B94),0) | D94: =C94*Paramètres!$B$3 | E94: =(Paramètres!$B$4*Paramètres!$B$6+IFERROR(INDEX(Données!$J$2:$J$190,$B94),0))*Paramètres!$B$3 | F94: =E94*Paramètres!$B$5 | G94: =IF(93=1,F94,G93+F94) | H94: =MIN(189,$B94+Paramètres!$B$7,COUNTIF(Données!$K$2:$K$190,"<="&G94)) | I94: =Paramètres!$B$4+IFERROR(INDEX(Données!$I$2:$I$190,$H94),0) | J94: =Paramètres!$B$4+IFERROR(INDEX(Données!$I$2:$I$190,MIN($H94,160)),0) | K94: =I94-J94 | L94: =IF(93=1,E94,L93+E94) | M94: =G94-IFERROR(INDEX(Données!$K$2:$K$190,$H94),0)
A95: 94 | B95: =IF(94=1,0,H94) | C95: =Paramètres!$B$4+IFERROR(INDEX(Données!$I$2:$I$190,$B95),0) | D95: =C95*Paramètres!$B$3 | E95: =(Paramètres!$B$4*Paramètres!$B$6+IFERROR(INDEX(Données!$J$2:$J$190,$B95),0))*Paramètres!$B$3 | F95: =E95*Paramètres!$B$5 | G95: =IF(94=1,F95,G94+F95) | H95: =MIN(189,$B95+Paramètres!$B$7,COUNTIF(Données!$K$2:$K$190,"<="&G95)) | I95: =Paramètres!$B$4+IFERROR(INDEX(Données!$I$2:$I$190,$H95),0) | J95: =Paramètres!$B$4+IFERROR(INDEX(Données!$I$2:$I$190,MIN($H95,160)),0) | K95: =I95-J95 | L95: =IF(94=1,E95,L94+E95) | M95: =G95-IFERROR(INDEX(Données!$K$2:$K$190,$H95),0)
A96: 95 | B96: =IF(95=1,0,H95) | C96: =Paramètres!$B$4+IFERROR(INDEX(Données!$I$2:$I$190,$B96),0) | D96: =C96*Paramètres!$B$3 | E96: =(Paramètres!$B$4*Paramètres!$B$6+IFERROR(INDEX(Données!$J$2:$J$190,$B96),0))*Paramètres!$B$3 | F96: =E96*Paramètres!$B$5 | G96: =IF(95=1,F96,G95+F96) | H96: =MIN(189,$B96+Paramètres!$B$7,COUNTIF(Données!$K$2:$K$190,"<="&G96)) | I96: =Paramètres!$B$4+IFERROR(INDEX(Données!$I$2:$I$190,$H96),0) | J96: =Paramètres!$B$4+IFERROR(INDEX(Données!$I$2:$I$190,MIN($H96,160)),0) | K96: =I96-J96 | L96: =IF(95=1,E96,L95+E96) | M96: =G96-IFERROR(INDEX(Données!$K$2:$K$190,$H96),0)
A97: 96 | B97: =IF(96=1,0,H96) | C97: =Paramètres!$B$4+IFERROR(INDEX(Données!$I$2:$I$190,$B97),0) | D97: =C97*Paramètres!$B$3 | E97: =(Paramètres!$B$4*Paramètres!$B$6+IFERROR(INDEX(Données!$J$2:$J$190,$B97),0))*Paramètres!$B$3 | F97: =E97*Paramètres!$B$5 | G97: =IF(96=1,F97,G96+F97) | H97: =MIN(189,$B97+Paramètres!$B$7,COUNTIF(Données!$K$2:$K$190,"<="&G97)) | I97: =Paramètres!$B$4+IFERROR(INDEX(Données!$I$2:$I$190,$H97),0) | J97: =Paramètres!$B$4+IFERROR(INDEX(Données!$I$2:$I$190,MIN($H97,160)),0) | K97: =I97-J97 | L97: =IF(96=1,E97,L96+E97) | M97: =G97-IFERROR(INDEX(Données!$K$2:$K$190,$H97),0)
A98: 97 | B98: =IF(97=1,0,H97) | C98: =Paramètres!$B$4+IFERROR(INDEX(Données!$I$2:$I$190,$B98),0) | D98: =C98*Paramètres!$B$3 | E98: =(Paramètres!$B$4*Paramètres!$B$6+IFERROR(INDEX(Données!$J$2:$J$190,$B98),0))*Paramètres!$B$3 | F98: =E98*Paramètres!$B$5 | G98: =IF(97=1,F98,G97+F98) | H98: =MIN(189,$B98+Paramètres!$B$7,COUNTIF(Données!$K$2:$K$190,"<="&G98)) | I98: =Paramètres!$B$4+IFERROR(INDEX(Données!$I$2:$I$190,$H98),0) | J98: =Paramètres!$B$4+IFERROR(INDEX(Données!$I$2:$I$190,MIN($H98,160)),0) | K98: =I98-J98 | L98: =IF(97=1,E98,L97+E98) | M98: =G98-IFERROR(INDEX(Données!$K$2:$K$190,$H98),0)
A99: 98 | B99: =IF(98=1,0,H98) | C99: =Paramètres!$B$4+IFERROR(INDEX(Données!$I$2:$I$190,$B99),0) | D99: =C99*Paramètres!$B$3 | E99: =(Paramètres!$B$4*Paramètres!$B$6+IFERROR(INDEX(Données!$J$2:$J$190,$B99),0))*Paramètres!$B$3 | F99: =E99*Paramètres!$B$5 | G99: =IF(98=1,F99,G98+F99) | H99: =MIN(189,$B99+Paramètres!$B$7,COUNTIF(Données!$K$2:$K$190,"<="&G99)) | I99: =Paramètres!$B$4+IFERROR(INDEX(Données!$I$2:$I$190,$H99),0) | J99: =Paramètres!$B$4+IFERROR(INDEX(Données!$I$2:$I$190,MIN($H99,160)),0) | K99: =I99-J99 | L99: =IF(98=1,E99,L98+E99) | M99: =G99-IFERROR(INDEX(Données!$K$2:$K$190,$H99),0)
A100: 99 | B100: =IF(99=1,0,H99) | C100: =Paramètres!$B$4+IFERROR(INDEX(Données!$I$2:$I$190,$B100),0) | D100: =C100*Paramètres!$B$3 | E100: =(Paramètres!$B$4*Paramètres!$B$6+IFERROR(INDEX(Données!$J$2:$J$190,$B100),0))*Paramètres!$B$3 | F100: =E100*Paramètres!$B$5 | G100: =IF(99=1,F100,G99+F100) | H100: =MIN(189,$B100+Paramètres!$B$7,COUNTIF(Données!$K$2:$K$190,"<="&G100)) | I100: =Paramètres!$B$4+IFERROR(INDEX(Données!$I$2:$I$190,$H100),0) | J100: =Paramètres!$B$4+IFERROR(INDEX(Données!$I$2:$I$190,MIN($H100,160)),0) | K100: =I100-J100 | L100: =IF(99=1,E100,L99+E100) | M100: =G100-IFERROR(INDEX(Données!$K$2:$K$190,$H100),0)
...

Sheet Graphiques
A1: Graphiques (se redessinent avec les paramètres)
